Workbook

Sheet Test Case Register
A1: AMC Core — Master Business Scenarios Test Case Register
A2: DocTypes: AMC Customers | AMC Contract | Vendor | Attendance | Expense Claim | Leave Application | Service Call | Total: 320 test cases | 27 Feb 2026
A4: Test ID | B4: DocType | C4: Module | D4: Test Case Title | E4: Priority | F4: Business Rule | G4: Status | H4: Executed By | I4: Execution Date | J4: Actual Result | K4: Defect ID | L4: Notes
A5: ▌ AMC Customers
A6: CUST-001 | B6: AMC Customers | C6: Customer Creation & Basic Details | D6: Create customer with Customer Name only (minimum required) | E6: Critical | F6: BR-CUST-01 | G6: Not Run
A7: CUST-002 | B7: AMC Customers | C7: Customer Creation & Basic Details | D7: Create Company customer with all basic fields (Name, Type, GST, PAN) | E7: Critical | F7: BR-CUST-01, BR-CUST-02 | G7: Not Run
A8: CUST-003 | B8: AMC Customers | C8: Customer Creation & Basic Details | D8: Create Individual customer type | E8: High | F8: BR-CUST-02 | G8: Not Run
A9: CUST-004 | B9: AMC Customers | C9: Customer Creation & Basic Details | D9: Create Partnership customer type | E9: High | F9: BR-CUST-02 | G9: Not Run
A10: CUST-005 | B10: AMC Customers | C10: GST Validation | D10: Valid 15-character GSTIN is accepted | E10: Critical | F10: BR-CUST-03 | G10: Not Run
A11: CUST-006 | B11: AMC Customers | C11: GST Validation | D11: Invalid GST format is rejected with specific error message | E11: Critical | F11: BR-CUST-03 | G11: Not Run
A12: CUST-007 | B12: AMC Customers | C12: GST Validation | D12: Duplicate GSTIN across two customers is blocked | E12: Critical | F12: BR-CUST-04 | G12: Not Run
A13: CUST-008 | B13: AMC Customers | C13: GST Validation | D13: GST field can be left blank (optional for Individual) | E13: High | F13: BR-CUST-03 | G13: Not Run
A14: CUST-009 | B14: AMC Customers | C14: GST Validation | D14: Duplicate PAN across two customers is blocked | E14: High | F14: BR-CUST-05 | G14: Not Run
A15: CUST-010 | B15: AMC Customers | C15: Branch Locations | D15: Add single branch location to customer | E15: Critical | F15: BR-CUST-06 | G15: Not Run
A16: CUST-011 | B16: AMC Customers | C16: Branch Locations | D16: Add multiple branch locations to same customer | E16: High | F16: BR-CUST-06 | G16: Not Run
A17: CUST-012 | B17: AMC Customers | C17: Branch Locations | D17: Delete a branch location row | E17: Medium | F17: BR-CUST-06 | G17: Not Run
... A26: CUST-021 | B26: AMC Customers | C26: Data Integrity | D26: Deleting customer with active contracts is blocked | E26: High | F26: BR-CUST-10 | G26: Not Run
A27: ▌ AMC Contract
A28: CON-001 | B28: AMC Contract | C28: Contract Creation | D28: Create AMC Contract with all mandatory fields | E28: Critical | F28: BR-CON-01 | G28: Not Run
A29: CON-002 | B29: AMC Contract | C29: Contract Creation | D29: Start Date is mandatory — save fails without it | E29: Critical | F29: BR-CON-01 | G29: Not Run
A30: CON-003 | B30: AMC Contract | C30: Contract Creation | D30: End Date is mandatory — save fails without it | E30: Critical | F30: BR-CON-01 | G30: Not Run
A31: CON-004 | B31: AMC Contract | C31: Contract Creation | D31: No of Services is mandatory — save fails without it | E31: Critical | F31: BR-CON-01 | G31: Not Run
A32: CON-005 | B32: AMC Contract | C32: Contract Creation | D32: Auto-naming follows AMC-.YY.MM.-.#### series | E32: High | F32: BR-CON-02 | G32: Not Run
A33: CON-006 | B33: AMC Contract | C33: Contract Date Logic | D33: End Date before Start Date is rejected | E33: Critical | F33: BR-CON-03 | G33: Not Run
A34: CON-007 | B34: AMC Contract | C34: Contract Date Logic | D34: Same Start and End Date is valid (single-day contract) | E34: High | F34: BR-CON-03 | G34: Not Run
A35: CON-008 | B35: AMC Contract | C35: Contract Date Logic | D35: Multi-year contract is valid (e.g., 2 years) | E35: High | F35: BR-CON-03 | G35: Not Run
A36: CON-009 | B36: AMC Contract | C36: Service Count & Schedule | D36: 4 services Jan-Dec creates exactly 4 Maintenance Schedule rows | E36: Critical | F36: BR-CON-04 | G36: Not Run
A37: CON-010 | B37: AMC Contract | C37: Service Count & Schedule | D37: 12 services creates 12 monthly Maintenance Schedule rows | E37: Critical | F37: BR-CON-04 | G37: Not Run
A38: CON-011 | B38: AMC Contract | C38: Service Count & Schedule | D38: 1 service creates exactly 1 Maintenance Schedule row | E38: Critical | F38: BR-CON-04 | G38: Not Run
A39: CON-012 | B39: AMC Contract | C39: Service Count & Schedule | D39: All schedule dates fall within contract Start-End range | E39: Critical | F39: BR-CON-05 | G39: Not Run
... A59: CON-032 | B59: AMC Contract | C59: Cross-DocType Integration | D59: Technician cannot cancel or delete AMC Contract | E59: Critical | F59: BR-CON-14 | G59: Not Run
A60: ▌ Vendor
A61: VEN-001 | B61: Vendor | C61: Vendor Creation & Basic Details | D61: Create Vendor with Vendor Name only (mandatory field) | E61: Critical | F61: BR-VEN-01 | G61: Not Run
A62: VEN-002 | B62: Vendor | C62: Vendor Creation & Basic Details | D62: Create Vendor with all basic fields (Name, Type, PAN) | E62: Critical | F62: BR-VEN-01, BR-VEN-02 | G62: Not Run
A63: VEN-003 | B63: Vendor | C63: Vendor Creation & Basic Details | D63: Create Vendor with Type as Company | E63: High | F63: BR-VEN-02 | G63: Not Run
A64: VEN-004 | B64: Vendor | C64: Vendor Creation & Basic Details | D64: Create Vendor with Type as Individual | E64: High | F64: BR-VEN-02 | G64: Not Run
A65: VEN-005 | B65: Vendor | C65: Primary Contact Details | D65: Add Primary Contact Person | E65: Critical | F65: BR-VEN-03 | G65: Not Run
A66: VEN-006 | B66: Vendor | C66: Primary Contact Details | D66: Valid phone number format in Mobile No field | E66: High | F66: BR-VEN-03 | G66: Not Run
A67: VEN-007 | B67: Vendor | C67: Primary Contact Details | D67: Invalid phone number format is rejected | E67: Critical | F67: BR-VEN-03 | G67: Not Run
A68: VEN-008 | B68: Vendor | C68: Primary Contact Details | D68: Valid email format is accepted | E68: High | F68: BR-VEN-03 | G68: Not Run
A69: VEN-009 | B69: Vendor | C69: Primary Contact Details | D69: Invalid email format is rejected with error message | E69: Critical | F69: BR-VEN-03 | G69: Not Run
A70: VEN-010 | B70: Vendor | C70: Tax Identification | D70: Valid PAN number format is accepted | E70: Critical | F70: BR-VEN-04 | G70: Not Run
A71: VEN-011 | B71: Vendor | C71: Tax Identification | D71: Invalid PAN format is rejected | E71: Critical | F71: BR-VEN-04 | G71: Not Run
A72: VEN-012 | B72: Vendor | C72: Tax Identification | D72: Duplicate PAN across two vendors is blocked | E72: Critical | F72: BR-VEN-05 | G72: Not Run
... A100: VEN-040 | B100: Vendor | C100: Form Actions | D100: Delete Vendor (if permitted) | E100: High | F100: BR-VEN-11 | G100: Not Run
A101: ▌ Attendance
A102: ATT-001 | B102: Attendance | C102: Attendance Creation & Basic Details | D102: Create Attendance with mandatory fields only (Employee, Status, Attendance Date) | E102: Critical | F102: BR-ATT-01 | G102: Not Run
A103: ATT-002 | B103: Attendance | C103: Attendance Creation & Basic Details | D103: Create Attendance with all basic fields (Employee, Status, Date, Company, Shift) | E103: Critical | F103: BR-ATT-01, BR-ATT-02 | G103: Not Run
A104: ATT-003 | B104: Attendance | C104: Attendance Creation & Basic Details | D104: Create Attendance with Status as Present | E104: Critical | F104: BR-ATT-03 | G104: Not Run
A105: ATT-004 | B105: Attendance | C105: Attendance Creation & Basic Details | D105: Create Attendance with Status as Absent | E105: Critical | F105: BR-ATT-03 | G105: Not Run
A106: ATT-005 | B106: Attendance | C106: Attendance Creation & Basic Details | D106: Create Attendance with Status as Leave | E106: High | F106: BR-ATT-03 | G106: Not Run
A107: ATT-006 | B107: Attendance | C107: Attendance Creation & Basic Details | D107: Create Attendance with Status as Half Day | E107: High | F107: BR-ATT-03 | G107: Not Run
A108: ATT-007 | B108: Attendance | C108: Series & Auto-generation | D108: Series field is auto-generated in format HR-ATT-.YYYY.- | E108: Critical | F108: BR-ATT-04 | G108: Not Run
A109: ATT-008 | B109: Attendance | C109: Series & Auto-generation | D109: Series field cannot be manually edited | E109: High | F109: BR-ATT-04 | G109: Not Run
A110: ATT-009 | B110: Attendance | C110: Series & Auto-generation | D110: Unique Series is generated for each attendance record | E110: Critical | F110: BR-ATT-04 | G110: Not Run
A111: ATT-010 | B111: Attendance | C111: Employee Selection | D111: Valid employee can be selected from dropdown | E111: Critical | F111: BR-ATT-05 | G111: Not Run
A112: ATT-011 | B112: Attendance | C112: Employee Selection | D112: Invalid/non-existent employee is rejected | E112: Critical | F112: BR-ATT-05 | G112: Not Run
A113: ATT-012 | B113: Attendance | C113: Employee Selection | D113: Employee field is mandatory and cannot be left blank | E113: Critical | F113: BR-ATT-05 | G113: Not Run
... A153: ATT-052 | B153: Attendance | C153: Form Actions | D153: Form shows "Saved" status after successful save | E153: Medium | F153: BR-ATT-14 | G153: Not Run
A154: ▌ Expense Claim
A155: EXP-001 | B155: Expense Claim | C155: Expense Claim Creation & Basic Details | D155: Create Expense Claim with mandatory fields only (From Employee, Expense Approver) | E155: Critical | F155: BR-EXP-01 | G155: Not Run
A156: EXP-002 | B156: Expense Claim | C156: Expense Claim Creation & Basic Details | D156: Create Expense Claim with all basic fields (Employee, Department, Company, Approver) | E156: Critical | F156: BR-EXP-01, BR-EXP-02 | G156: Not Run
A157: EXP-003 | B157: Expense Claim | C157: Series & Auto-generation | D157: Series field is auto-generated in format HR-EXP-.YYYY.- | E157: Critical | F157: BR-EXP-03 | G157: Not Run
A158: EXP-004 | B158: Expense Claim | C158: Series & Auto-generation | D158: Series field cannot be manually edited | E158: High | F158: BR-EXP-03 | G158: Not Run
A159: EXP-005 | B159: Expense Claim | C159: Series & Auto-generation | D159: Unique Series is generated for each expense claim record | E159: Critical | F159: BR-EXP-03 | G159: Not Run
A160: EXP-006 | B160: Expense Claim | C160: Employee Selection | D160: Valid employee can be selected in From Employee field | E160: Critical | F160: BR-EXP-04 | G160: Not Run
A161: EXP-007 | B161: Expense Claim | C161: Employee Selection | D161: Invalid/non-existent employee is rejected | E161: Critical | F161: BR-EXP-04 | G161: Not Run
A162: EXP-008 | B162: Expense Claim | C162: Employee Selection | D162: From Employee field is mandatory and cannot be left blank | E162: Critical | F162: BR-EXP-04 | G162: Not Run
A163: EXP-009 | B163: Expense Claim | C163: Employee Selection | D163: Department auto-populates based on selected employee | E163: High | F163: BR-EXP-04 | G163: Not Run
A164: EXP-010 | B164: Expense Claim | C164: Company Details | D164: Valid company is selected and displayed | E164: Critical | F164: BR-EXP-05 | G164: Not Run
A165: EXP-011 | B165: Expense Claim | C165: Company Details | D165: Company field is mandatory | E165: Critical | F165: BR-EXP-05 | G165: Not Run
A166: EXP-012 | B166: Expense Claim | C166: Company Details | D166: Company GSTIN is auto-populated based on selected company | E166: High | F166: BR-EXP-05 | G166: Not Run
... A214: EXP-060 | B214: Expense Claim | C214: Form Actions | D214: Cancel submitted Expense Claim | E214: Critical | F214: BR-EXP-16 | G214: Not Run
A215: ▌ Leave Application
A216: LEA-001 | B216: Leave Application | C216: Leave Application Creation & Basic Details | D216: Create Leave Application with mandatory fields only (Employee, Leave Type, From Date, To Date) | E216: Critical | F216: BR-LEA-01 | G216: Not Run
A217: LEA-002 | B217: Leave Application | C217: Leave Application Creation & Basic Details | D217: Create Leave Application with all basic fields (Employee, Leave Type, Dates, Company, Approver) | E217: Critical | F217: BR-LEA-01, BR-LEA-02 | G217: Not Run
A218: LEA-003 | B218: Leave Application | C218: Series & Auto-generation | D218: Series field is auto-generated in format HR-LAP-.YYYY.- | E218: Critical | F218: BR-LEA-03 | G218: Not Run
A219: LEA-004 | B219: Leave Application | C219: Series & Auto-generation | D219: Series field cannot be manually edited | E219: High | F219: BR-LEA-03 | G219: Not Run
A220: LEA-005 | B220: Leave Application | C220: Series & Auto-generation | D220: Unique Series is generated for each leave application | E220: Critical | F220: BR-LEA-03 | G220: Not Run
A221: LEA-006 | B221: Leave Application | C221: Employee Selection | D221: Valid employee can be selected in Employee field | E221: Critical | F221: BR-LEA-04 | G221: Not Run
A222: LEA-007 | B222: Leave Application | C222: Employee Selection | D222: Invalid/non-existent employee is rejected | E222: Critical | F222: BR-LEA-04 | G222: Not Run
A223: LEA-008 | B223: Leave Application | C223: Employee Selection | D223: Employee field is mandatory and cannot be left blank | E223: Critical | F223: BR-LEA-04 | G223: Not Run
A224: LEA-009 | B224: Leave Application | C224: Leave Type Selection | D224: Valid leave type can be selected from dropdown | E224: Critical | F224: BR-LEA-05 | G224: Not Run
A225: LEA-010 | B225: Leave Application | C225: Leave Type Selection | D225: Leave Type field is mandatory and cannot be left blank | E225: Critical | F225: BR-LEA-05 | G225: Not Run
A226: LEA-011 | B226: Leave Application | C226: Leave Type Selection | D226: Leave Type displays all available options (Annual, Sick, Personal, etc.) | E226: High | F226: BR-LEA-05 | G226: Not Run
A227: LEA-012 | B227: Leave Application | C227: Leave Type Selection | D227: Employee's leave balance is checked for selected leave type | E227: Critical | F227: BR-LEA-06 | G227: Not Run
... A280: LEA-065 | B280: Leave Application | C280: Form Actions | D280: Delete Draft Leave Application | E280: High | F280: BR-LEA-16 | G280: Not Run
A281: ▌ Service Call
A282: SC-001 | B282: Service Call | C282: Service Call Creation & Basic Details | D282: Create Service Call with mandatory fields only (Customer, Service Type) | E282: Critical | F282: BR-SC-01 | G282: Not Run
A283: SC-002 | B283: Service Call | C283: Service Call Creation & Basic Details | D283: Create Service Call with all basic fields (Customer, Title, Description, Priority) | E283: Critical | F283: BR-SC-01, BR-SC-02 | G283: Not Run
A284: SC-003 | B284: Service Call | C284: Service Call Creation & Basic Details | D284: Create Service Call with multiple Service Items | E284: High | F284: BR-SC-08 | G284: Not Run
A285: SC-004 | B285: Service Call | C285: Service Call Creation & Basic Details | D285: Create Service Call for Individual customer type | E285: High | F285: BR-SC-03 | G285: Not Run
A286: SC-005 | B286: Service Call | C286: Service Call Creation & Basic Details | D286: Create Service Call for Company customer type | E286: High | F286: BR-SC-03 | G286: Not Run
A287: SC-006 | B287: Service Call | C287: Customer & Location Validation | D287: Valid customer selection populates branch locations | E287: Critical | F287: BR-SC-03 | G287: Not Run
A288: SC-007 | B288: Service Call | C288: Customer & Location Validation | D288: Invalid/non-existent customer is rejected | E288: Critical | F288: BR-SC-03 | G288: Not Run
A289: SC-008 | B289: Service Call | C289: Customer & Location Validation | D289: Service Call can be linked to specific branch location | E289: High | F289: BR-SC-04 | G289: Not Run
A290: SC-009 | B290: Service Call | C290: Customer & Location Validation | D290: Contact person is filtered by selected branch | E290: High | F290: BR-SC-04 | G290: Not Run
A291: SC-010 | B291: Service Call | C291: Technician Assignment | D291: Assign available technician to Service Call | E291: Critical | F291: BR-SC-05 | G291: Not Run
A292: SC-011 | B292: Service Call | C292: Technician Assignment | D292: Reassign technician to different Service Call | E292: High | F292: BR-SC-05 | G292: Not Run
A293: SC-012 | B293: Service Call | C293: Technician Assignment | D293: Service Call without technician assignment is saved successfully | E293: Medium | F293: BR-SC-05 | G293: Not Run
...

Sheet Run Tracker
A1: AMC Core — Master Test Execution Run Tracker
A2: Each Run column = one full execution cycle. Formulas auto-calculate pass rate per test case.
A4: Test ID | B4: DocType | C4: Module | D4: Title | E4: Priority | F4: Run 1 | G4: Run 2 | H4: Run 3 | I4: Run 4 | J4: Run 5 | K4: Run 6 | L4: Total Runs | M4: Pass | N4: Fail | O4: Pass Rate
A5: ▌ AMC Customers
A6: CUST-001 | B6: AMC Customers | C6: Customer Creation & Basic Details | D6: Create customer with Customer Name only (minimum required) | E6: Critical | F6: Not Run | G6: Not Run | H6: Not Run | I6: Not Run | J6: Not Run | K6: Not Run | L6: =COUNTA(F6:K6) -> 6 | M6: =COUNTIF(F6:K6,"Pass") -> 0 | N6: =COUNTIF(F6:K6,"Fail") -> 0 | O6: =IF(M6=0,"-",M6/L6) -> -
A7: CUST-002 | B7: AMC Customers | C7: Customer Creation & Basic Details | D7: Create Company customer with all basic fields (Name, Type, GST, PAN) | E7: Critical | F7: Not Run | G7: Not Run | H7: Not Run | I7: Not Run | J7: Not Run | K7: Not Run | L7: =COUNTA(F7:K7) -> 6 | M7: =COUNTIF(F7:K7,"Pass") -> 0 | N7: =COUNTIF(F7:K7,"Fail") -> 0 | O7: =IF(M7=0,"-",M7/L7) -> -
A8: CUST-003 | B8: AMC Customers | C8: Customer Creation & Basic Details | D8: Create Individual customer type | E8: High | F8: Not Run | G8: Not Run | H8: Not Run | I8: Not Run | J8: Not Run | K8: Not Run | L8: =COUNTA(F8:K8) -> 6 | M8: =COUNTIF(F8:K8,"Pass") -> 0 | N8: =COUNTIF(F8:K8,"Fail") -> 0 | O8: =IF(M8=0,"-",M8/L8) -> -
A9: CUST-004 | B9: AMC Customers | C9: Customer Creation & Basic Details | D9: Create Partnership customer type | E9: High | F9: Not Run | G9: Not Run | H9: Not Run | I9: Not Run | J9: Not Run | K9: Not Run | L9: =COUNTA(F9:K9) -> 6 | M9: =COUNTIF(F9:K9,"Pass") -> 0 | N9: =COUNTIF(F9:K9,"Fail") -> 0 | O9: =IF(M9=0,"-",M9/L9) -> -
A10: CUST-005 | B10: AMC Customers | C10: GST Validation | D10: Valid 15-character GSTIN is accepted | E10: Critical | F10: Not Run | G10: Not Run | H10: Not Run | I10: Not Run | J10: Not Run | K10: Not Run | L10: =COUNTA(F10:K10) -> 6 | M10: =COUNTIF(F10:K10,"Pass") -> 0 | N10: =COUNTIF(F10:K10,"Fail") -> 0 | O10: =IF(M10=0,"-",M10/L10) -> -
A11: CUST-006 | B11: AMC Customers | C11: GST Validation | D11: Invalid GST format is rejected with specific error message | E11: Critical | F11: Not Run | G11: Not Run | H11: Not Run | I11: Not Run | J11: Not Run | K11: Not Run | L11: =COUNTA(F11:K11) -> 6 | M11: =COUNTIF(F11:K11,"Pass") -> 0 | N11: =COUNTIF(F11:K11,"Fail") -> 0 | O11: =IF(M11=0,"-",M11/L11) -> -
A12: CUST-007 | B12: AMC Customers | C12: GST Validation | D12: Duplicate GSTIN across two customers is blocked | E12: Critical | F12: Not Run | G12: Not Run | H12: Not Run | I12: Not Run | J12: Not Run | K12: Not Run | L12: =COUNTA(F12:K12) -> 6 | M12: =COUNTIF(F12:K12,"Pass") -> 0 | N12: =COUNTIF(F12:K12,"Fail") -> 0 | O12: =IF(M12=0,"-",M12/L12) -> -
A13: CUST-008 | B13: AMC Customers | C13: GST Validation | D13: GST field can be left blank (optional for Individual) | E13: High | F13: Not Run | G13: Not Run | H13: Not Run | I13: Not Run | J13: Not Run | K13: Not Run | L13: =COUNTA(F13:K13) -> 6 | M13: =COUNTIF(F13:K13,"Pass") -> 0 | N13: =COUNTIF(F13:K13,"Fail") -> 0 | O13: =IF(M13=0,"-",M13/L13) -> -
A14: CUST-009 | B14: AMC Customers | C14: GST Validation | D14: Duplicate PAN across two customers is blocked | E14: High | F14: Not Run | G14: Not Run | H14: Not Run | I14: Not Run | J14: Not Run | K14: Not Run | L14: =COUNTA(F14:K14) -> 6 | M14: =COUNTIF(F14:K14,"Pass") -> 0 | N14: =COUNTIF(F14:K14,"Fail") -> 0 | O14: =IF(M14=0,"-",M14/L14) -> -
A15: CUST-010 | B15: AMC Customers | C15: Branch Locations | D15: Add single branch location to customer | E15: Critical | F15: Not Run | G15: Not Run | H15: Not Run | I15: Not Run | J15: Not Run | K15: Not Run | L15: =COUNTA(F15:K15) -> 6 | M15: =COUNTIF(F15:K15,"Pass") -> 0 | N15: =COUNTIF(F15:K15,"Fail") -> 0 | O15: =IF(M15=0,"-",M15/L15) -> -
A16: CUST-011 | B16: AMC Customers | C16: Branch Locations | D16: Add multiple branch locations to same customer | E16: High | F16: Not Run | G16: Not Run | H16: Not Run | I16: Not Run | J16: Not Run | K16: Not Run | L16: =COUNTA(F16:K16) -> 6 | M16: =COUNTIF(F16:K16,"Pass") -> 0 | N16: =COUNTIF(F16:K16,"Fail") -> 0 | O16: =IF(M16=0,"-",M16/L16) -> -
A17: CUST-012 | B17: AMC Customers | C17: Branch Locations | D17: Delete a branch location row | E17: Medium | F17: Not Run | G17: Not Run | H17: Not Run | I17: Not Run | J17: Not Run | K17: Not Run | L17: =COUNTA(F17:K17) -> 6 | M17: =COUNTIF(F17:K17,"Pass") -> 0 | N17: =COUNTIF(F17:K17,"Fail") -> 0 | O17: =IF(M17=0,"-",M17/L17) -> -
... A26: CUST-021 | B26: AMC Customers | C26: Data Integrity | D26: Deleting customer with active contracts is blocked | E26: High | F26: Not Run | G26: Not Run | H26: Not Run | I26: Not Run | J26: Not Run | K26: Not Run | L26: =COUNTA(F26:K26) -> 6 | M26: =COUNTIF(F26:K26,"Pass") -> 0 | N26: =COUNTIF(F26:K26,"Fail") -> 0 | O26: =IF(M26=0,"-",M26/L26) -> -
A27: ▌ AMC Contract
A28: CON-001 | B28: AMC Contract | C28: Contract Creation | D28: Create AMC Contract with all mandatory fields | E28: Critical | F28: Not Run | G28: Not Run | H28: Not Run | I28: Not Run | J28: Not Run | K28: Not Run | L28: =COUNTA(F28:K28) -> 6 | M28: =COUNTIF(F28:K28,"Pass") -> 0 | N28: =COUNTIF(F28:K28,"Fail") -> 0 | O28: =IF(M28=0,"-",M28/L28) -> -
A29: CON-002 | B29: AMC Contract | C29: Contract Creation | D29: Start Date is mandatory — save fails without it | E29: Critical | F29: Not Run | G29: Not Run | H29: Not Run | I29: Not Run | J29: Not Run | K29: Not Run | L29: =COUNTA(F29:K29) -> 6 | M29: =COUNTIF(F29:K29,"Pass") -> 0 | N29: =COUNTIF(F29:K29,"Fail") -> 0 | O29: =IF(M29=0,"-",M29/L29) -> -
A30: CON-003 | B30: AMC Contract | C30: Contract Creation | D30: End Date is mandatory — save fails without it | E30: Critical | F30: Not Run | G30: Not Run | H30: Not Run | I30: Not Run | J30: Not Run | K30: Not Run | L30: =COUNTA(F30:K30) -> 6 | M30: =COUNTIF(F30:K30,"Pass") -> 0 | N30: =COUNTIF(F30:K30,"Fail") -> 0 | O30: =IF(M30=0,"-",M30/L30) -> -
A31: CON-004 | B31: AMC Contract | C31: Contract Creation | D31: No of Services is mandatory — save fails without it | E31: Critical | F31: Not Run | G31: Not Run | H31: Not Run | I31: Not Run | J31: Not Run | K31: Not Run | L31: =COUNTA(F31:K31) -> 6 | M31: =COUNTIF(F31:K31,"Pass") -> 0 | N31: =COUNTIF(F31:K31,"Fail") -> 0 | O31: =IF(M31=0,"-",M31/L31) -> -
A32: CON-005 | B32: AMC Contract | C32: Contract Creation | D32: Auto-naming follows AMC-.YY.MM.-.#### series | E32: High | F32: Not Run | G32: Not Run | H32: Not Run | I32: Not Run | J32: Not Run | K32: Not Run | L32: =COUNTA(F32:K32) -> 6 | M32: =COUNTIF(F32:K32,"Pass") -> 0 | N32: =COUNTIF(F32:K32,"Fail") -> 0 | O32: =IF(M32=0,"-",M32/L32) -> -
A33: CON-006 | B33: AMC Contract | C33: Contract Date Logic | D33: End Date before Start Date is rejected | E33: Critical | F33: Not Run | G33: Not Run | H33: Not Run | I33: Not Run | J33: Not Run | K33: Not Run | L33: =COUNTA(F33:K33) -> 6 | M33: =COUNTIF(F33:K33,"Pass") -> 0 | N33: =COUNTIF(F33:K33,"Fail") -> 0 | O33: =IF(M33=0,"-",M33/L33) -> -
A34: CON-007 | B34: AMC Contract | C34: Contract Date Logic | D34: Same Start and End Date is valid (single-day contract) | E34: High | F34: Not Run | G34: Not Run | H34: Not Run | I34: Not Run | J34: Not Run | K34: Not Run | L34: =COUNTA(F34:K34) -> 6 | M34: =COUNTIF(F34:K34,"Pass") -> 0 | N34: =COUNTIF(F34:K34,"Fail") -> 0 | O34: =IF(M34=0,"-",M34/L34) -> -
A35: CON-008 | B35: AMC Contract | C35: Contract Date Logic | D35: Multi-year contract is valid (e.g., 2 years) | E35: High | F35: Not Run | G35: Not Run | H35: Not Run | I35: Not Run | J35: Not Run | K35: Not Run | L35: =COUNTA(F35:K35) -> 6 | M35: =COUNTIF(F35:K35,"Pass") -> 0 | N35: =COUNTIF(F35:K35,"Fail") -> 0 | O35: =IF(M35=0,"-",M35/L35) -> -
A36: CON-009 | B36: AMC Contract | C36: Service Count & Schedule | D36: 4 services Jan-Dec creates exactly 4 Maintenance Schedule rows | E36: Critical | F36: Not Run | G36: Not Run | H36: Not Run | I36: Not Run | J36: Not Run | K36: Not Run | L36: =COUNTA(F36:K36) -> 6 | M36: =COUNTIF(F36:K36,"Pass") -> 0 | N36: =COUNTIF(F36:K36,"Fail") -> 0 | O36: =IF(M36=0,"-",M36/L36) -> -
A37: CON-010 | B37: AMC Contract | C37: Service Count & Schedule | D37: 12 services creates 12 monthly Maintenance Schedule rows | E37: Critical | F37: Not Run | G37: Not Run | H37: Not Run | I37: Not Run | J37: Not Run | K37: Not Run | L37: =COUNTA(F37:K37) -> 6 | M37: =COUNTIF(F37:K37,"Pass") -> 0 | N37: =COUNTIF(F37:K37,"Fail") -> 0 | O37: =IF(M37=0,"-",M37/L37) -> -
A38: CON-011 | B38: AMC Contract | C38: Service Count & Schedule | D38: 1 service creates exactly 1 Maintenance Schedule row | E38: Critical | F38: Not Run | G38: Not Run | H38: Not Run | I38: Not Run | J38: Not Run | K38: Not Run | L38: =COUNTA(F38:K38) -> 6 | M38: =COUNTIF(F38:K38,"Pass") -> 0 | N38: =COUNTIF(F38:K38,"Fail") -> 0 | O38: =IF(M38=0,"-",M38/L38) -> -
A39: CON-012 | B39: AMC Contract | C39: Service Count & Schedule | D39: All schedule dates fall within contract Start-End range | E39: Critical | F39: Not Run | G39: Not Run | H39: Not Run | I39: Not Run | J39: Not Run | K39: Not Run | L39: =COUNTA(F39:K39) -> 6 | M39: =COUNTIF(F39:K39,"Pass") -> 0 | N39: =COUNTIF(F39:K39,"Fail") -> 0 | O39: =IF(M39=0,"-",M39/L39) -> -
... A59: CON-032 | B59: AMC Contract | C59: Cross-DocType Integration | D59: Technician cannot cancel or delete AMC Contract | E59: Critical | F59: Not Run | G59: Not Run | H59: Not Run | I59: Not Run | J59: Not Run | K59: Not Run | L59: =COUNTA(F59:K59) -> 6 | M59: =COUNTIF(F59:K59,"Pass") -> 0 | N59: =COUNTIF(F59:K59,"Fail") -> 0 | O59: =IF(M59=0,"-",M59/L59) -> -
A60: ▌ Vendor
A61: VEN-001 | B61: Vendor | C61: Vendor Creation & Basic Details | D61: Create Vendor with Vendor Name only (mandatory field) | E61: Critical | F61: Not Run | G61: Not Run | H61: Not Run | I61: Not Run | J61: Not Run | K61: Not Run | L61: =COUNTA(F61:K61) -> 6 | M61: =COUNTIF(F61:K61,"Pass") -> 0 | N61: =COUNTIF(F61:K61,"Fail") -> 0 | O61: =IF(M61=0,"-",M61/L61) -> -
A62: VEN-002 | B62: Vendor | C62: Vendor Creation & Basic Details | D62: Create Vendor with all basic fields (Name, Type, PAN) | E62: Critical | F62: Not Run | G62: Not Run | H62: Not Run | I62: Not Run | J62: Not Run | K62: Not Run | L62: =COUNTA(F62:K62) -> 6 | M62: =COUNTIF(F62:K62,"Pass") -> 0 | N62: =COUNTIF(F62:K62,"Fail") -> 0 | O62: =IF(M62=0,"-",M62/L62) -> -
A63: VEN-003 | B63: Vendor | C63: Vendor Creation & Basic Details | D63: Create Vendor with Type as Company | E63: High | F63: Not Run | G63: Not Run | H63: Not Run | I63: Not Run | J63: Not Run | K63: Not Run | L63: =COUNTA(F63:K63) -> 6 | M63: =COUNTIF(F63:K63,"Pass") -> 0 | N63: =COUNTIF(F63:K63,"Fail") -> 0 | O63: =IF(M63=0,"-",M63/L63) -> -
A64: VEN-004 | B64: Vendor | C64: Vendor Creation & Basic Details | D64: Create Vendor with Type as Individual | E64: High | F64: Not Run | G64: Not Run | H64: Not Run | I64: Not Run | J64: Not Run | K64: Not Run | L64: =COUNTA(F64:K64) -> 6 | M64: =COUNTIF(F64:K64,"Pass") -> 0 | N64: =COUNTIF(F64:K64,"Fail") -> 0 | O64: =IF(M64=0,"-",M64/L64) -> -
A65: VEN-005 | B65: Vendor | C65: Primary Contact Details | D65: Add Primary Contact Person | E65: Critical | F65: Not Run | G65: Not Run | H65: Not Run | I65: Not Run | J65: Not Run | K65: Not Run | L65: =COUNTA(F65:K65) -> 6 | M65: =COUNTIF(F65:K65,"Pass") -> 0 | N65: =COUNTIF(F65:K65,"Fail") -> 0 | O65: =IF(M65=0,"-",M65/L65) -> -
A66: VEN-006 | B66: Vendor | C66: Primary Contact Details | D66: Valid phone number format in Mobile No field | E66: High | F66: Not Run | G66: Not Run | H66: Not Run | I66: Not Run | J66: Not Run | K66: Not Run | L66: =COUNTA(F66:K66) -> 6 | M66: =COUNTIF(F66:K66,"Pass") -> 0 | N66: =COUNTIF(F66:K66,"Fail") -> 0 | O66: =IF(M66=0,"-",M66/L66) -> -
A67: VEN-007 | B67: Vendor | C67: Primary Contact Details | D67: Invalid phone number format is rejected | E67: Critical | F67: Not Run | G67: Not Run | H67: Not Run | I67: Not Run | J67: Not Run | K67: Not Run | L67: =COUNTA(F67:K67) -> 6 | M67: =COUNTIF(F67:K67,"Pass") -> 0 | N67: =COUNTIF(F67:K67,"Fail") -> 0 | O67: =IF(M67=0,"-",M67/L67) -> -
A68: VEN-008 | B68: Vendor | C68: Primary Contact Details | D68: Valid email format is accepted | E68: High | F68: Not Run | G68: Not Run | H68: Not Run | I68: Not Run | J68: Not Run | K68: Not Run | L68: =COUNTA(F68:K68) -> 6 | M68: =COUNTIF(F68:K68,"Pass") -> 0 | N68: =COUNTIF(F68:K68,"Fail") -> 0 | O68: =IF(M68=0,"-",M68/L68) -> -
A69: VEN-009 | B69: Vendor | C69: Primary Contact Details | D69: Invalid email format is rejected with error message | E69: Critical | F69: Not Run | G69: Not Run | H69: Not Run | I69: Not Run | J69: Not Run | K69: Not Run | L69: =COUNTA(F69:K69) -> 6 | M69: =COUNTIF(F69:K69,"Pass") -> 0 | N69: =COUNTIF(F69:K69,"Fail") -> 0 | O69: =IF(M69=0,"-",M69/L69) -> -
A70: VEN-010 | B70: Vendor | C70: Tax Identification | D70: Valid PAN number format is accepted | E70: Critical | F70: Not Run | G70: Not Run | H70: Not Run | I70: Not Run | J70: Not Run | K70: Not Run | L70: =COUNTA(F70:K70) -> 6 | M70: =COUNTIF(F70:K70,"Pass") -> 0 | N70: =COUNTIF(F70:K70,"Fail") -> 0 | O70: =IF(M70=0,"-",M70/L70) -> -
A71: VEN-011 | B71: Vendor | C71: Tax Identification | D71: Invalid PAN format is rejected | E71: Critical | F71: Not Run | G71: Not Run | H71: Not Run | I71: Not Run | J71: Not Run | K71: Not Run | L71: =COUNTA(F71:K71) -> 6 | M71: =COUNTIF(F71:K71,"Pass") -> 0 | N71: =COUNTIF(F71:K71,"Fail") -> 0 | O71: =IF(M71=0,"-",M71/L71) -> -
A72: VEN-012 | B72: Vendor | C72: Tax Identification | D72: Duplicate PAN across two vendors is blocked | E72: Critical | F72: Not Run | G72: Not Run | H72: Not Run | I72: Not Run | J72: Not Run | K72: Not Run | L72: =COUNTA(F72:K72) -> 6 | M72: =COUNTIF(F72:K72,"Pass") -> 0 | N72: =COUNTIF(F72:K72,"Fail") -> 0 | O72: =IF(M72=0,"-",M72/L72) -> -
... A100: VEN-040 | B100: Vendor | C100: Form Actions | D100: Delete Vendor (if permitted) | E100: High | F100: Not Run | G100: Not Run | H100: Not Run | I100: Not Run | J100: Not Run | K100: Not Run | L100: =COUNTA(F100:K100) -> 6 | M100: =COUNTIF(F100:K100,"Pass") -> 0 | N100: =COUNTIF(F100:K100,"Fail") -> 0 | O100: =IF(M100=0,"-",M100/L100) -> -
A101: ▌ Attendance
A102: ATT-001 | B102: Attendance | C102: Attendance Creation & Basic Details | D102: Create Attendance with mandatory fields only (Employee, Status, Attendance Date) | E102: Critical | F102: Not Run | G102: Not Run | H102: Not Run | I102: Not Run | J102: Not Run | K102: Not Run | L102: =COUNTA(F102:K102) -> 6 | M102: =COUNTIF(F102:K102,"Pass") -> 0 | N102: =COUNTIF(F102:K102,"Fail") -> 0 | O102: =IF(M102=0,"-",M102/L102) -> -
A103: ATT-002 | B103: Attendance | C103: Attendance Creation & Basic Details | D103: Create Attendance with all basic fields (Employee, Status, Date, Company, Shift) | E103: Critical | F103: Not Run | G103: Not Run | H103: Not Run | I103: Not Run | J103: Not Run | K103: Not Run | L103: =COUNTA(F103:K103) -> 6 | M103: =COUNTIF(F103:K103,"Pass") -> 0 | N103: =COUNTIF(F103:K103,"Fail") -> 0 | O103: =IF(M103=0,"-",M103/L103) -> -
A104: ATT-003 | B104: Attendance | C104: Attendance Creation & Basic Details | D104: Create Attendance with Status as Present | E104: Critical | F104: Not Run | G104: Not Run | H104: Not Run | I104: Not Run | J104: Not Run | K104: Not Run | L104: =COUNTA(F104:K104) -> 6 | M104: =COUNTIF(F104:K104,"Pass") -> 0 | N104: =COUNTIF(F104:K104,"Fail") -> 0 | O104: =IF(M104=0,"-",M104/L104) -> -
A105: ATT-004 | B105: Attendance | C105: Attendance Creation & Basic Details | D105: Create Attendance with Status as Absent | E105: Critical | F105: Not Run | G105: Not Run | H105: Not Run | I105: Not Run | J105: Not Run | K105: Not Run | L105: =COUNTA(F105:K105) -> 6 | M105: =COUNTIF(F105:K105,"Pass") -> 0 | N105: =COUNTIF(F105:K105,"Fail") -> 0 | O105: =IF(M105=0,"-",M105/L105) -> -
A106: ATT-005 | B106: Attendance | C106: Attendance Creation & Basic Details | D106: Create Attendance with Status as Leave | E106: High | F106: Not Run | G106: Not Run | H106: Not Run | I106: Not Run | J106: Not Run | K106: Not Run | L106: =COUNTA(F106:K106) -> 6 | M106: =COUNTIF(F106:K106,"Pass") -> 0 | N106: =COUNTIF(F106:K106,"Fail") -> 0 | O106: =IF(M106=0,"-",M106/L106) -> -
A107: ATT-006 | B107: Attendance | C107: Attendance Creation & Basic Details | D107: Create Attendance with Status as Half Day | E107: High | F107: Not Run | G107: Not Run | H107: Not Run | I107: Not Run | J107: Not Run | K107: Not Run | L107: =COUNTA(F107:K107) -> 6 | M107: =COUNTIF(F107:K107,"Pass") -> 0 | N107: =COUNTIF(F107:K107,"Fail") -> 0 | O107: =IF(M107=0,"-",M107/L107) -> -
A108: ATT-007 | B108: Attendance | C108: Series & Auto-generation | D108: Series field is auto-generated in format HR-ATT-.YYYY.- | E108: Critical | F108: Not Run | G108: Not Run | H108: Not Run | I108: Not Run | J108: Not Run | K108: Not Run | L108: =COUNTA(F108:K108) -> 6 | M108: =COUNTIF(F108:K108,"Pass") -> 0 | N108: =COUNTIF(F108:K108,"Fail") -> 0 | O108: =IF(M108=0,"-",M108/L108) -> -
A109: ATT-008 | B109: Attendance | C109: Series & Auto-generation | D109: Series field cannot be manually edited | E109: High | F109: Not Run | G109: Not Run | H109: Not Run | I109: Not Run | J109: Not Run | K109: Not Run | L109: =COUNTA(F109:K109) -> 6 | M109: =COUNTIF(F109:K109,"Pass") -> 0 | N109: =COUNTIF(F109:K109,"Fail") -> 0 | O109: =IF(M109=0,"-",M109/L109) -> -
A110: ATT-009 | B110: Attendance | C110: Series & Auto-generation | D110: Unique Series is generated for each attendance record | E110: Critical | F110: Not Run | G110: Not Run | H110: Not Run | I110: Not Run | J110: Not Run | K110: Not Run | L110: =COUNTA(F110:K110) -> 6 | M110: =COUNTIF(F110:K110,"Pass") -> 0 | N110: =COUNTIF(F110:K110,"Fail") -> 0 | O110: =IF(M110=0,"-",M110/L110) -> -
A111: ATT-010 | B111: Attendance | C111: Employee Selection | D111: Valid employee can be selected from dropdown | E111: Critical | F111: Not Run | G111: Not Run | H111: Not Run | I111: Not Run | J111: Not Run | K111: Not Run | L111: =COUNTA(F111:K111) -> 6 | M111: =COUNTIF(F111:K111,"Pass") -> 0 | N111: =COUNTIF(F111:K111,"Fail") -> 0 | O111: =IF(M111=0,"-",M111/L111) -> -
A112: ATT-011 | B112: Attendance | C112: Employee Selection | D112: Invalid/non-existent employee is rejected | E112: Critical | F112: Not Run | G112: Not Run | H112: Not Run | I112: Not Run | J112: Not Run | K112: Not Run | L112: =COUNTA(F112:K112) -> 6 | M112: =COUNTIF(F112:K112,"Pass") -> 0 | N112: =COUNTIF(F112:K112,"Fail") -> 0 | O112: =IF(M112=0,"-",M112/L112) -> -
A113: ATT-012 | B113: Attendance | C113: Employee Selection | D113: Employee field is mandatory and cannot be left blank | E113: Critical | F113: Not Run | G113: Not Run | H113: Not Run | I113: Not Run | J113: Not Run | K113: Not Run | L113: =COUNTA(F113:K113) -> 6 | M113: =COUNTIF(F113:K113,"Pass") -> 0 | N113: =COUNTIF(F113:K113,"Fail") -> 0 | O113: =IF(M113=0,"-",M113/L113) -> -
... A153: ATT-052 | B153: Attendance | C153: Form Actions | D153: Form shows "Saved" status after successful save | E153: Medium | F153: Not Run | G153: Not Run | H153: Not Run | I153: Not Run | J153: Not Run | K153: Not Run | L153: =COUNTA(F153:K153) -> 6 | M153: =COUNTIF(F153:K153,"Pass") -> 0 | N153: =COUNTIF(F153:K153,"Fail") -> 0 | O153: =IF(M153=0,"-",M153/L153) -> -
A154: ▌ Expense Claim
A155: EXP-001 | B155: Expense Claim | C155: Expense Claim Creation & Basic Details | D155: Create Expense Claim with mandatory fields only (From Employee, Expense Approver) | E155: Critical | F155: Not Run | G155: Not Run | H155: Not Run | I155: Not Run | J155: Not Run | K155: Not Run | L155: =COUNTA(F155:K155) -> 6 | M155: =COUNTIF(F155:K155,"Pass") -> 0 | N155: =COUNTIF(F155:K155,"Fail") -> 0 | O155: =IF(M155=0,"-",M155/L155) -> -
A156: EXP-002 | B156: Expense Claim | C156: Expense Claim Creation & Basic Details | D156: Create Expense Claim with all basic fields (Employee, Department, Company, Approver) | E156: Critical | F156: Not Run | G156: Not Run | H156: Not Run | I156: Not Run | J156: Not Run | K156: Not Run | L156: =COUNTA(F156:K156) -> 6 | M156: =COUNTIF(F156:K156,"Pass") -> 0 | N156: =COUNTIF(F156:K156,"Fail") -> 0 | O156: =IF(M156=0,"-",M156/L156) -> -
A157: EXP-003 | B157: Expense Claim | C157: Series & Auto-generation | D157: Series field is auto-generated in format HR-EXP-.YYYY.- | E157: Critical | F157: Not Run | G157: Not Run | H157: Not Run | I157: Not Run | J157: Not Run | K157: Not Run | L157: =COUNTA(F157:K157) -> 6 | M157: =COUNTIF(F157:K157,"Pass") -> 0 | N157: =COUNTIF(F157:K157,"Fail") -> 0 | O157: =IF(M157=0,"-",M157/L157) -> -
A158: EXP-004 | B158: Expense Claim | C158: Series & Auto-generation | D158: Series field cannot be manually edited | E158: High | F158: Not Run | G158: Not Run | H158: Not Run | I158: Not Run | J158: Not Run | K158: Not Run | L158: =COUNTA(F158:K158) -> 6 | M158: =COUNTIF(F158:K158,"Pass") -> 0 | N158: =COUNTIF(F158:K158,"Fail") -> 0 | O158: =IF(M158=0,"-",M158/L158) -> -
A159: EXP-005 | B159: Expense Claim | C159: Series & Auto-generation | D159: Unique Series is generated for each expense claim record | E159: Critical | F159: Not Run | G159: Not Run | H159: Not Run | I159: Not Run | J159: Not Run | K159: Not Run | L159: =COUNTA(F159:K159) -> 6 | M159: =COUNTIF(F159:K159,"Pass") -> 0 | N159: =COUNTIF(F159:K159,"Fail") -> 0 | O159: =IF(M159=0,"-",M159/L159) -> -
A160: EXP-006 | B160: Expense Claim | C160: Employee Selection | D160: Valid employee can be selected in From Employee field | E160: Critical | F160: Not Run | G160: Not Run | H160: Not Run | I160: Not Run | J160: Not Run | K160: Not Run | L160: =COUNTA(F160:K160) -> 6 | M160: =COUNTIF(F160:K160,"Pass") -> 0 | N160: =COUNTIF(F160:K160,"Fail") -> 0 | O160: =IF(M160=0,"-",M160/L160) -> -
A161: EXP-007 | B161: Expense Claim | C161: Employee Selection | D161: Invalid/non-existent employee is rejected | E161: Critical | F161: Not Run | G161: Not Run | H161: Not Run | I161: Not Run | J161: Not Run | K161: Not Run | L161: =COUNTA(F161:K161) -> 6 | M161: =COUNTIF(F161:K161,"Pass") -> 0 | N161: =COUNTIF(F161:K161,"Fail") -> 0 | O161: =IF(M161=0,"-",M161/L161) -> -
A162: EXP-008 | B162: Expense Claim | C162: Employee Selection | D162: From Employee field is mandatory and cannot be left blank | E162: Critical | F162: Not Run | G162: Not Run | H162: Not Run | I162: Not Run | J162: Not Run | K162: Not Run | L162: =COUNTA(F162:K162) -> 6 | M162: =COUNTIF(F162:K162,"Pass") -> 0 | N162: =COUNTIF(F162:K162,"Fail") -> 0 | O162: =IF(M162=0,"-",M162/L162) -> -
A163: EXP-009 | B163: Expense Claim | C163: Employee Selection | D163: Department auto-populates based on selected employee | E163: High | F163: Not Run | G163: Not Run | H163: Not Run | I163: Not Run | J163: Not Run | K163: Not Run | L163: =COUNTA(F163:K163) -> 6 | M163: =COUNTIF(F163:K163,"Pass") -> 0 | N163: =COUNTIF(F163:K163,"Fail") -> 0 | O163: =IF(M163=0,"-",M163/L163) -> -
A164: EXP-010 | B164: Expense Claim | C164: Company Details | D164: Valid company is selected and displayed | E164: Critical | F164: Not Run | G164: Not Run | H164: Not Run | I164: Not Run | J164: Not Run | K164: Not Run | L164: =COUNTA(F164:K164) -> 6 | M164: =COUNTIF(F164:K164,"Pass") -> 0 | N164: =COUNTIF(F164:K164,"Fail") -> 0 | O164: =IF(M164=0,"-",M164/L164) -> -
A165: EXP-011 | B165: Expense Claim | C165: Company Details | D165: Company field is mandatory | E165: Critical | F165: Not Run | G165: Not Run | H165: Not Run | I165: Not Run | J165: Not Run | K165: Not Run | L165: =COUNTA(F165:K165) -> 6 | M165: =COUNTIF(F165:K165,"Pass") -> 0 | N165: =COUNTIF(F165:K165,"Fail") -> 0 | O165: =IF(M165=0,"-",M165/L165) -> -
A166: EXP-012 | B166: Expense Claim | C166: Company Details | D166: Company GSTIN is auto-populated based on selected company | E166: High | F166: Not Run | G166: Not Run | H166: Not Run | I166: Not Run | J166: Not Run | K166: Not Run | L166: =COUNTA(F166:K166) -> 6 | M166: =COUNTIF(F166:K166,"Pass") -> 0 | N166: =COUNTIF(F166:K166,"Fail") -> 0 | O166: =IF(M166=0,"-",M166/L166) -> -
... A214: EXP-060 | B214: Expense Claim | C214: Form Actions | D214: Cancel submitted Expense Claim | E214: Critical | F214: Not Run | G214: Not Run | H214: Not Run | I214: Not Run | J214: Not Run | K214: Not Run | L214: =COUNTA(F214:K214) -> 6 | M214: =COUNTIF(F214:K214,"Pass") -> 0 | N214: =COUNTIF(F214:K214,"Fail") -> 0 | O214: =IF(M214=0,"-",M214/L214) -> -
A215: ▌ Leave Application
A216: LEA-001 | B216: Leave Application | C216: Leave Application Creation & Basic Details | D216: Create Leave Application with mandatory fields only (Employee, Leave Type, From Date, To Date) | E216: Critical | F216: Not Run | G216: Not Run | H216: Not Run | I216: Not Run | J216: Not Run | K216: Not Run | L216: =COUNTA(F216:K216) -> 6 | M216: =COUNTIF(F216:K216,"Pass") -> 0 | N216: =COUNTIF(F216:K216,"Fail") -> 0 | O216: =IF(M216=0,"-",M216/L216) -> -
A217: LEA-002 | B217: Leave Application | C217: Leave Application Creation & Basic Details | D217: Create Leave Application with all basic fields (Employee, Leave Type, Dates, Company, Approver) | E217: Critical | F217: Not Run | G217: Not Run | H217: Not Run | I217: Not Run | J217: Not Run | K217: Not Run | L217: =COUNTA(F217:K217) -> 6 | M217: =COUNTIF(F217:K217,"Pass") -> 0 | N217: =COUNTIF(F217:K217,"Fail") -> 0 | O217: =IF(M217=0,"-",M217/L217) -> -
A218: LEA-003 | B218: Leave Application | C218: Series & Auto-generation | D218: Series field is auto-generated in format HR-LAP-.YYYY.- | E218: Critical | F218: Not Run | G218: Not Run | H218: Not Run | I218: Not Run | J218: Not Run | K218: Not Run | L218: =COUNTA(F218:K218) -> 6 | M218: =COUNTIF(F218:K218,"Pass") -> 0 | N218: =COUNTIF(F218:K218,"Fail") -> 0 | O218: =IF(M218=0,"-",M218/L218) -> -
A219: LEA-004 | B219: Leave Application | C219: Series & Auto-generation | D219: Series field cannot be manually edited | E219: High | F219: Not Run | G219: Not Run | H219: Not Run | I219: Not Run | J219: Not Run | K219: Not Run | L219: =COUNTA(F219:K219) -> 6 | M219: =COUNTIF(F219:K219,"Pass") -> 0 | N219: =COUNTIF(F219:K219,"Fail") -> 0 | O219: =IF(M219=0,"-",M219/L219) -> -
A220: LEA-005 | B220: Leave Application | C220: Series & Auto-generation | D220: Unique Series is generated for each leave application | E220: Critical | F220: Not Run | G220: Not Run | H220: Not Run | I220: Not Run | J220: Not Run | K220: Not Run | L220: =COUNTA(F220:K220) -> 6 | M220: =COUNTIF(F220:K220,"Pass") -> 0 | N220: =COUNTIF(F220:K220,"Fail") -> 0 | O220: =IF(M220=0,"-",M220/L220) -> -
A221: LEA-006 | B221: Leave Application | C221: Employee Selection | D221: Valid employee can be selected in Employee field | E221: Critical | F221: Not Run | G221: Not Run | H221: Not Run | I221: Not Run | J221: Not Run | K221: Not Run | L221: =COUNTA(F221:K221) -> 6 | M221: =COUNTIF(F221:K221,"Pass") -> 0 | N221: =COUNTIF(F221:K221,"Fail") -> 0 | O221: =IF(M221=0,"-",M221/L221) -> -
A222: LEA-007 | B222: Leave Application | C222: Employee Selection | D222: Invalid/non-existent employee is rejected | E222: Critical | F222: Not Run | G222: Not Run | H222: Not Run | I222: Not Run | J222: Not Run | K222: Not Run | L222: =COUNTA(F222:K222) -> 6 | M222: =COUNTIF(F222:K222,"Pass") -> 0 | N222: =COUNTIF(F222:K222,"Fail") -> 0 | O222: =IF(M222=0,"-",M222/L222) -> -
A223: LEA-008 | B223: Leave Application | C223: Employee Selection | D223: Employee field is mandatory and cannot be left blank | E223: Critical | F223: Not Run | G223: Not Run | H223: Not Run | I223: Not Run | J223: Not Run | K223: Not Run | L223: =COUNTA(F223:K223) -> 6 | M223: =COUNTIF(F223:K223,"Pass") -> 0 | N223: =COUNTIF(F223:K223,"Fail") -> 0 | O223: =IF(M223=0,"-",M223/L223) -> -
A224: LEA-009 | B224: Leave Application | C224: Leave Type Selection | D224: Valid leave type can be selected from dropdown | E224: Critical | F224: Not Run | G224: Not Run | H224: Not Run | I224: Not Run | J224: Not Run | K224: Not Run | L224: =COUNTA(F224:K224) -> 6 | M224: =COUNTIF(F224:K224,"Pass") -> 0 | N224: =COUNTIF(F224:K224,"Fail") -> 0 | O224: =IF(M224=0,"-",M224/L224) -> -
A225: LEA-010 | B225: Leave Application | C225: Leave Type Selection | D225: Leave Type field is mandatory and cannot be left blank | E225: Critical | F225: Not Run | G225: Not Run | H225: Not Run | I225: Not Run | J225: Not Run | K225: Not Run | L225: =COUNTA(F225:K225) -> 6 | M225: =COUNTIF(F225:K225,"Pass") -> 0 | N225: =COUNTIF(F225:K225,"Fail") -> 0 | O225: =IF(M225=0,"-",M225/L225) -> -
A226: LEA-011 | B226: Leave Application | C226: Leave Type Selection | D226: Leave Type displays all available options (Annual, Sick, Personal, etc.) | E226: High | F226: Not Run | G226: Not Run | H226: Not Run | I226: Not Run | J226: Not Run | K226: Not Run | L226: =COUNTA(F226:K226) -> 6 | M226: =COUNTIF(F226:K226,"Pass") -> 0 | N226: =COUNTIF(F226:K226,"Fail") -> 0 | O226: =IF(M226=0,"-",M226/L226) -> -
A227: LEA-012 | B227: Leave Application | C227: Leave Type Selection | D227: Employee's leave balance is checked for selected leave type | E227: Critical | F227: Not Run | G227: Not Run | H227: Not Run | I227: Not Run | J227: Not Run | K227: Not Run | L227: =COUNTA(F227:K227) -> 6 | M227: =COUNTIF(F227:K227,"Pass") -> 0 | N227: =COUNTIF(F227:K227,"Fail") -> 0 | O227: =IF(M227=0,"-",M227/L227) -> -
... A280: LEA-065 | B280: Leave Application | C280: Form Actions | D280: Delete Draft Leave Application | E280: High | F280: Not Run | G280: Not Run | H280: Not Run | I280: Not Run | J280: Not Run | K280: Not Run | L280: =COUNTA(F280:K280) -> 6 | M280: =COUNTIF(F280:K280,"Pass") -> 0 | N280: =COUNTIF(F280:K280,"Fail") -> 0 | O280: =IF(M280=0,"-",M280/L280) -> -
A281: ▌ Service Call
A282: SC-001 | B282: Service Call | C282: Service Call Creation & Basic Details | D282: Create Service Call with mandatory fields only (Customer, Service Type) | E282: Critical | F282: Not Run | G282: Not Run | H282: Not Run | I282: Not Run | J282: Not Run | K282: Not Run | L282: =COUNTA(F282:K282) -> 6 | M282: =COUNTIF(F282:K282,"Pass") -> 0 | N282: =COUNTIF(F282:K282,"Fail") -> 0 | O282: =IF(M282=0,"-",M282/L282) -> -
A283: SC-002 | B283: Service Call | C283: Service Call Creation & Basic Details | D283: Create Service Call with all basic fields (Customer, Title, Description, Priority) | E283: Critical | F283: Not Run | G283: Not Run | H283: Not Run | I283: Not Run | J283: Not Run | K283: Not Run | L283: =COUNTA(F283:K283) -> 6 | M283: =COUNTIF(F283:K283,"Pass") -> 0 | N283: =COUNTIF(F283:K283,"Fail") -> 0 | O283: =IF(M283=0,"-",M283/L283) -> -
A284: SC-003 | B284: Service Call | C284: Service Call Creation & Basic Details | D284: Create Service Call with multiple Service Items | E284: High | F284: Not Run | G284: Not Run | H284: Not Run | I284: Not Run | J284: Not Run | K284: Not Run | L284: =COUNTA(F284:K284) -> 6 | M284: =COUNTIF(F284:K284,"Pass") -> 0 | N284: =COUNTIF(F284:K284,"Fail") -> 0 | O284: =IF(M284=0,"-",M284/L284) -> -
A285: SC-004 | B285: Service Call | C285: Service Call Creation & Basic Details | D285: Create Service Call for Individual customer type | E285: High | F285: Not Run | G285: Not Run | H285: Not Run | I285: Not Run | J285: Not Run | K285: Not Run | L285: =COUNTA(F285:K285) -> 6 | M285: =COUNTIF(F285:K285,"Pass") -> 0 | N285: =COUNTIF(F285:K285,"Fail") -> 0 | O285: =IF(M285=0,"-",M285/L285) -> -
A286: SC-005 | B286: Service Call | C286: Service Call Creation & Basic Details | D286: Create Service Call for Company customer type | E286: High | F286: Not Run | G286: Not Run | H286: Not Run | I286: Not Run | J286: Not Run | K286: Not Run | L286: =COUNTA(F286:K286) -> 6 | M286: =COUNTIF(F286:K286,"Pass") -> 0 | N286: =COUNTIF(F286:K286,"Fail") -> 0 | O286: =IF(M286=0,"-",M286/L286) -> -
A287: SC-006 | B287: Service Call | C287: Customer & Location Validation | D287: Valid customer selection populates branch locations | E287: Critical | F287: Not Run | G287: Not Run | H287: Not Run | I287: Not Run | J287: Not Run | K287: Not Run | L287: =COUNTA(F287:K287) -> 6 | M287: =COUNTIF(F287:K287,"Pass") -> 0 | N287: =COUNTIF(F287:K287,"Fail") -> 0 | O287: =IF(M287=0,"-",M287/L287) -> -
A288: SC-007 | B288: Service Call | C288: Customer & Location Validation | D288: Invalid/non-existent customer is rejected | E288: Critical | F288: Not Run | G288: Not Run | H288: Not Run | I288: Not Run | J288: Not Run | K288: Not Run | L288: =COUNTA(F288:K288) -> 6 | M288: =COUNTIF(F288:K288,"Pass") -> 0 | N288: =COUNTIF(F288:K288,"Fail") -> 0 | O288: =IF(M288=0,"-",M288/L288) -> -
A289: SC-008 | B289: Service Call | C289: Customer & Location Validation | D289: Service Call can be linked to specific branch location | E289: High | F289: Not Run | G289: Not Run | H289: Not Run | I289: Not Run | J289: Not Run | K289: Not Run | L289: =COUNTA(F289:K289) -> 6 | M289: =COUNTIF(F289:K289,"Pass") -> 0 | N289: =COUNTIF(F289:K289,"Fail") -> 0 | O289: =IF(M289=0,"-",M289/L289) -> -
A290: SC-009 | B290: Service Call | C290: Customer & Location Validation | D290: Contact person is filtered by selected branch | E290: High | F290: Not Run | G290: Not Run | H290: Not Run | I290: Not Run | J290: Not Run | K290: Not Run | L290: =COUNTA(F290:K290) -> 6 | M290: =COUNTIF(F290:K290,"Pass") -> 0 | N290: =COUNTIF(F290:K290,"Fail") -> 0 | O290: =IF(M290=0,"-",M290/L290) -> -
A291: SC-010 | B291: Service Call | C291: Technician Assignment | D291: Assign available technician to Service Call | E291: Critical | F291: Not Run | G291: Not Run | H291: Not Run | I291: Not Run | J291: Not Run | K291: Not Run | L291: =COUNTA(F291:K291) -> 6 | M291: =COUNTIF(F291:K291,"Pass") -> 0 | N291: =COUNTIF(F291:K291,"Fail") -> 0 | O291: =IF(M291=0,"-",M291/L291) -> -
A292: SC-011 | B292: Service Call | C292: Technician Assignment | D292: Reassign technician to different Service Call | E292: High | F292: Not Run | G292: Not Run | H292: Not Run | I292: Not Run | J292: Not Run | K292: Not Run | L292: =COUNTA(F292:K292) -> 6 | M292: =COUNTIF(F292:K292,"Pass") -> 0 | N292: =COUNTIF(F292:K292,"Fail") -> 0 | O292: =IF(M292=0,"-",M292/L292) -> -
A293: SC-012 | B293: Service Call | C293: Technician Assignment | D293: Service Call without technician assignment is saved successfully | E293: Medium | F293: Not Run | G293: Not Run | H293: Not Run | I293: Not Run | J293: Not Run | K293: Not Run | L293: =COUNTA(F293:K293) -> 6 | M293: =COUNTIF(F293:K293,"Pass") -> 0 | N293: =COUNTIF(F293:K293,"Fail") -> 0 | O293: =IF(M293=0,"-",M293/L293) -> -
...

Sheet Run Summary
A1: AMC Core — Master Execution Summary Dashboard
A2: Live dashboard — all metrics auto-update as Test Case Register statuses are filled in.
A4: Total TCs | C4: Not Run | E4: Pass | G4: Fail | I4: Blocked | K4: Pass Rate
A5: =COUNTA('Test Case Register'!A5:A700)-COUNTIF('Test Case Register'!A5:A700,"▌*") -> 320 | C5: =COUNTIF('Test Case Register'!G5:G700,"Not Run") -> 320 | E5: =COUNTIF('Test Case Register'!G5:G700,"Pass") -> 0 | G5: =COUNTIF('Test Case Register'!G5:G700,"Fail") -> 0 | I5: =COUNTIF('Test Case Register'!G5:G700,"Blocked") -> 0 | K5: =IF(COUNTIF('Test Case Register'!G5:G700,"Pass")+COUNTIF('Test Case Register'!G5:G700,"Fail")=0,0,COUNTIF('Test Case Register'!G5:G700,"Pass")/(COUNTIF('Test Case Register'!G5:G700,"Pass")+COUNTIF('Test Case Register'!G5:G700,"Fail"))) -> 0
A7: Results by DocType
A8: DocType | C8: Total | E8: Pass | G8: Fail | I8: Blocked | K8: Pass Rate
A9: AMC Customers | C9: 21 | E9: =COUNTIFS('Test Case Register'!B5:B700,"AMC Customers",'Test Case Register'!G5:G700,"Pass") -> 0 | G9: =COUNTIFS('Test Case Register'!B5:B700,"AMC Customers",'Test Case Register'!G5:G700,"Fail") -> 0 | I9: =COUNTIFS('Test Case Register'!B5:B700,"AMC Customers",'Test Case Register'!G5:G700,"Blocked") -> 0 | K9: =IF(E9+G9=0,"-",E9/(E9+G9)) -> -
A10: AMC Contract | C10: 32 | E10: =COUNTIFS('Test Case Register'!B5:B700,"AMC Contract",'Test Case Register'!G5:G700,"Pass") -> 0 | G10: =COUNTIFS('Test Case Register'!B5:B700,"AMC Contract",'Test Case Register'!G5:G700,"Fail") -> 0 | I10: =COUNTIFS('Test Case Register'!B5:B700,"AMC Contract",'Test Case Register'!G5:G700,"Blocked") -> 0 | K10: =IF(E10+G10=0,"-",E10/(E10+G10)) -> -
A11: Vendor | C11: 40 | E11: =COUNTIFS('Test Case Register'!B5:B700,"Vendor",'Test Case Register'!G5:G700,"Pass") -> 0 | G11: =COUNTIFS('Test Case Register'!B5:B700,"Vendor",'Test Case Register'!G5:G700,"Fail") -> 0 | I11: =COUNTIFS('Test Case Register'!B5:B700,"Vendor",'Test Case Register'!G5:G700,"Blocked") -> 0 | K11: =IF(E11+G11=0,"-",E11/(E11+G11)) -> -
A12: Attendance | C12: 52 | E12: =COUNTIFS('Test Case Register'!B5:B700,"Attendance",'Test Case Register'!G5:G700,"Pass") -> 0 | G12: =COUNTIFS('Test Case Register'!B5:B700,"Attendance",'Test Case Register'!G5:G700,"Fail") -> 0 | I12: =COUNTIFS('Test Case Register'!B5:B700,"Attendance",'Test Case Register'!G5:G700,"Blocked") -> 0 | K12: =IF(E12+G12=0,"-",E12/(E12+G12)) -> -
A13: Expense Claim | C13: 60 | E13: =COUNTIFS('Test Case Register'!B5:B700,"Expense Claim",'Test Case Register'!G5:G700,"Pass") -> 0 | G13: =COUNTIFS('Test Case Register'!B5:B700,"Expense Claim",'Test Case Register'!G5:G700,"Fail") -> 0 | I13: =COUNTIFS('Test Case Register'!B5:B700,"Expense Claim",'Test Case Register'!G5:G700,"Blocked") -> 0 | K13: =IF(E13+G13=0,"-",E13/(E13+G13)) -> -
A14: Leave Application | C14: 65 | E14: =COUNTIFS('Test Case Register'!B5:B700,"Leave Application",'Test Case Register'!G5:G700,"Pass") -> 0 | G14: =COUNTIFS('Test Case Register'!B5:B700,"Leave Application",'Test Case Register'!G5:G700,"Fail") -> 0 | I14: =COUNTIFS('Test Case Register'!B5:B700,"Leave Application",'Test Case Register'!G5:G700,"Blocked") -> 0 | K14: =IF(E14+G14=0,"-",E14/(E14+G14)) -> -
A15: Service Call | C15: 50 | E15: =COUNTIFS('Test Case Register'!B5:B700,"Service Call",'Test Case Register'!G5:G700,"Pass") -> 0 | G15: =COUNTIFS('Test Case Register'!B5:B700,"Service Call",'Test Case Register'!G5:G700,"Fail") -> 0 | I15: =COUNTIFS('Test Case Register'!B5:B700,"Service Call",'Test Case Register'!G5:G700,"Blocked") -> 0 | K15: =IF(E15+G15=0,"-",E15/(E15+G15)) -> -
A18: Results by Module
A19: Module | B19: DocType | C19: Tests | D19: Pass | E19: Fail | F19: Blocked | G19: Pass Rate
A20: Customer Creation & Basic Details | B20: AMC Customers | C20: 4 | D20: =COUNTIFS('Test Case Register'!B5:B700,"AMC Customers",'Test Case Register'!C5:C700,"Customer Creation & Basic Details",'Test Case Register'!G5:G700,"Pass") -> 0 | E20: =COUNTIFS('Test Case Register'!B5:B700,"AMC Customers",'Test Case Register'!C5:C700,"Customer Creation & Basic Details",'Test Case Register'!G5:G700,"Fail") -> 0 | F20: =COUNTIFS('Test Case Register'!B5:B700,"AMC Customers",'Test Case Register'!C5:C700,"Customer Creation & Basic Details",'Test Case Register'!G5:G700,"Blocked") -> 0 | G20: =IF(D20+E20=0,"-",D20/(D20+E20)) -> -
A21: GST Validation | B21: AMC Customers | C21: 5 | D21: =COUNTIFS('Test Case Register'!B5:B700,"AMC Customers",'Test Case Register'!C5:C700,"GST Validation",'Test Case Register'!G5:G700,"Pass") -> 0 | E21: =COUNTIFS('Test Case Register'!B5:B700,"AMC Customers",'Test Case Register'!C5:C700,"GST Validation",'Test Case Register'!G5:G700,"Fail") -> 0 | F21: =COUNTIFS('Test Case Register'!B5:B700,"AMC Customers",'Test Case Register'!C5:C700,"GST Validation",'Test Case Register'!G5:G700,"Blocked") -> 0 | G21: =IF(D21+E21=0,"-",D21/(D21+E21)) -> -
A22: Branch Locations | B22: AMC Customers | C22: 4 | D22: =COUNTIFS('Test Case Register'!B5:B700,"AMC Customers",'Test Case Register'!C5:C700,"Branch Locations",'Test Case Register'!G5:G700,"Pass") -> 0 | E22: =COUNTIFS('Test Case Register'!B5:B700,"AMC Customers",'Test Case Register'!C5:C700,"Branch Locations",'Test Case Register'!G5:G700,"Fail") -> 0 | F22: =COUNTIFS('Test Case Register'!B5:B700,"AMC Customers",'Test Case Register'!C5:C700,"Branch Locations",'Test Case Register'!G5:G700,"Blocked") -> 0 | G22: =IF(D22+E22=0,"-",D22/(D22+E22)) -> -
A23: Contact Details | B23: AMC Customers | C23: 4 | D23: =COUNTIFS('Test Case Register'!B5:B700,"AMC Customers",'Test Case Register'!C5:C700,"Contact Details",'Test Case Register'!G5:G700,"Pass") -> 0 | E23: =COUNTIFS('Test Case Register'!B5:B700,"AMC Customers",'Test Case Register'!C5:C700,"Contact Details",'Test Case Register'!G5:G700,"Fail") -> 0 | F23: =COUNTIFS('Test Case Register'!B5:B700,"AMC Customers",'Test Case Register'!C5:C700,"Contact Details",'Test Case Register'!G5:G700,"Blocked") -> 0 | G23: =IF(D23+E23=0,"-",D23/(D23+E23)) -> -
A24: Connections Tab | B24: AMC Customers | C24: 2 | D24: =COUNTIFS('Test Case Register'!B5:B700,"AMC Customers",'Test Case Register'!C5:C700,"Connections Tab",'Test Case Register'!G5:G700,"Pass") -> 0 | E24: =COUNTIFS('Test Case Register'!B5:B700,"AMC Customers",'Test Case Register'!C5:C700,"Connections Tab",'Test Case Register'!G5:G700,"Fail") -> 0 | F24: =COUNTIFS('Test Case Register'!B5:B700,"AMC Customers",'Test Case Register'!C5:C700,"Connections Tab",'Test Case Register'!G5:G700,"Blocked") -> 0 | G24: =IF(D24+E24=0,"-",D24/(D24+E24)) -> -
A25: Permissions | B25: AMC Customers | C25: 1 | D25: =COUNTIFS('Test Case Register'!B5:B700,"AMC Customers",'Test Case Register'!C5:C700,"Permissions",'Test Case Register'!G5:G700,"Pass") -> 0 | E25: =COUNTIFS('Test Case Register'!B5:B700,"AMC Customers",'Test Case Register'!C5:C700,"Permissions",'Test Case Register'!G5:G700,"Fail") -> 0 | F25: =COUNTIFS('Test Case Register'!B5:B700,"AMC Customers",'Test Case Register'!C5:C700,"Permissions",'Test Case Register'!G5:G700,"Blocked") -> 0 | G25: =IF(D25+E25=0,"-",D25/(D25+E25)) -> -
A26: Data Integrity | B26: AMC Customers | C26: 1 | D26: =COUNTIFS('Test Case Register'!B5:B700,"AMC Customers",'Test Case Register'!C5:C700,"Data Integrity",'Test Case Register'!G5:G700,"Pass") -> 0 | E26: =COUNTIFS('Test Case Register'!B5:B700,"AMC Customers",'Test Case Register'!C5:C700,"Data Integrity",'Test Case Register'!G5:G700,"Fail") -> 0 | F26: =COUNTIFS('Test Case Register'!B5:B700,"AMC Customers",'Test Case Register'!C5:C700,"Data Integrity",'Test Case Register'!G5:G700,"Blocked") -> 0 | G26: =IF(D26+E26=0,"-",D26/(D26+E26)) -> -
A27: Contract Creation | B27: AMC Contract | C27: 5 | D27: =COUNTIFS('Test Case Register'!B5:B700,"AMC Contract",'Test Case Register'!C5:C700,"Contract Creation",'Test Case Register'!G5:G700,"Pass") -> 0 | E27: =COUNTIFS('Test Case Register'!B5:B700,"AMC Contract",'Test Case Register'!C5:C700,"Contract Creation",'Test Case Register'!G5:G700,"Fail") -> 0 | F27: =COUNTIFS('Test Case Register'!B5:B700,"AMC Contract",'Test Case Register'!C5:C700,"Contract Creation",'Test Case Register'!G5:G700,"Blocked") -> 0 | G27: =IF(D27+E27=0,"-",D27/(D27+E27)) -> -
A28: Contract Date Logic | B28: AMC Contract | C28: 3 | D28: =COUNTIFS('Test Case Register'!B5:B700,"AMC Contract",'Test Case Register'!C5:C700,"Contract Date Logic",'Test Case Register'!G5:G700,"Pass") -> 0 | E28: =COUNTIFS('Test Case Register'!B5:B700,"AMC Contract",'Test Case Register'!C5:C700,"Contract Date Logic",'Test Case Register'!G5:G700,"Fail") -> 0 | F28: =COUNTIFS('Test Case Register'!B5:B700,"AMC Contract",'Test Case Register'!C5:C700,"Contract Date Logic",'Test Case Register'!G5:G700,"Blocked") -> 0 | G28: =IF(D28+E28=0,"-",D28/(D28+E28)) -> -
A29: Service Count & Schedule | B29: AMC Contract | C29: 6 | D29: =COUNTIFS('Test Case Register'!B5:B700,"AMC Contract",'Test Case Register'!C5:C700,"Service Count & Schedule",'Test Case Register'!G5:G700,"Pass") -> 0 | E29: =COUNTIFS('Test Case Register'!B5:B700,"AMC Contract",'Test Case Register'!C5:C700,"Service Count & Schedule",'Test Case Register'!G5:G700,"Fail") -> 0 | F29: =COUNTIFS('Test Case Register'!B5:B700,"AMC Contract",'Test Case Register'!C5:C700,"Service Count & Schedule",'Test Case Register'!G5:G700,"Blocked") -> 0 | G29: =IF(D29+E29=0,"-",D29/(D29+E29)) -> -
A30: Customer & Branch Linkage | B30: AMC Contract | C30: 4 | D30: =COUNTIFS('Test Case Register'!B5:B700,"AMC Contract",'Test Case Register'!C5:C700,"Customer & Branch Linkage",'Test Case Register'!G5:G700,"Pass") -> 0 | E30: =COUNTIFS('Test Case Register'!B5:B700,"AMC Contract",'Test Case Register'!C5:C700,"Customer & Branch Linkage",'Test Case Register'!G5:G700,"Fail") -> 0 | F30: =COUNTIFS('Test Case Register'!B5:B700,"AMC Contract",'Test Case Register'!C5:C700,"Customer & Branch Linkage",'Test Case Register'!G5:G700,"Blocked") -> 0 | G30: =IF(D30+E30=0,"-",D30/(D30+E30)) -> -
A31: Contract Status | B31: AMC Contract | C31: 3 | D31: =COUNTIFS('Test Case Register'!B5:B700,"AMC Contract",'Test Case Register'!C5:C700,"Contract Status",'Test Case Register'!G5:G700,"Pass") -> 0 | E31: =COUNTIFS('Test Case Register'!B5:B700,"AMC Contract",'Test Case Register'!C5:C700,"Contract Status",'Test Case Register'!G5:G700,"Fail") -> 0 | F31: =COUNTIFS('Test Case Register'!B5:B700,"AMC Contract",'Test Case Register'!C5:C700,"Contract Status",'Test Case Register'!G5:G700,"Blocked") -> 0 | G31: =IF(D31+E31=0,"-",D31/(D31+E31)) -> -
A32: Submit & Amend Workflow | B32: AMC Contract | C32: 4 | D32: =COUNTIFS('Test Case Register'!B5:B700,"AMC Contract",'Test Case Register'!C5:C700,"Submit & Amend Workflow",'Test Case Register'!G5:G700,"Pass") -> 0 | E32: =COUNTIFS('Test Case Register'!B5:B700,"AMC Contract",'Test Case Register'!C5:C700,"Submit & Amend Workflow",'Test Case Register'!G5:G700,"Fail") -> 0 | F32: =COUNTIFS('Test Case Register'!B5:B700,"AMC Contract",'Test Case Register'!C5:C700,"Submit & Amend Workflow",'Test Case Register'!G5:G700,"Blocked") -> 0 | G32: =IF(D32+E32=0,"-",D32/(D32+E32)) -> -
A33: Company Branch | B33: AMC Contract | C33: 1 | D33: =COUNTIFS('Test Case Register'!B5:B700,"AMC Contract",'Test Case Register'!C5:C700,"Company Branch",'Test Case Register'!G5:G700,"Pass") -> 0 | E33: =COUNTIFS('Test Case Register'!B5:B700,"AMC Contract",'Test Case Register'!C5:C700,"Company Branch",'Test Case Register'!G5:G700,"Fail") -> 0 | F33: =COUNTIFS('Test Case Register'!B5:B700,"AMC Contract",'Test Case Register'!C5:C700,"Company Branch",'Test Case Register'!G5:G700,"Blocked") -> 0 | G33: =IF(D33+E33=0,"-",D33/(D33+E33)) -> -
A34: Service Calls Tab | B34: AMC Contract | C34: 3 | D34: =COUNTIFS('Test Case Register'!B5:B700,"AMC Contract",'Test Case Register'!C5:C700,"Service Calls Tab",'Test Case Register'!G5:G700,"Pass") -> 0 | E34: =COUNTIFS('Test Case Register'!B5:B700,"AMC Contract",'Test Case Register'!C5:C700,"Service Calls Tab",'Test Case Register'!G5:G700,"Fail") -> 0 | F34: =COUNTIFS('Test Case Register'!B5:B700,"AMC Contract",'Test Case Register'!C5:C700,"Service Calls Tab",'Test Case Register'!G5:G700,"Blocked") -> 0 | G34: =IF(D34+E34=0,"-",D34/(D34+E34)) -> -
A35: Cross-DocType Integration | B35: AMC Contract | C35: 3 | D35: =COUNTIFS('Test Case Register'!B5:B700,"AMC Contract",'Test Case Register'!C5:C700,"Cross-DocType Integration",'Test Case Register'!G5:G700,"Pass") -> 0 | E35: =COUNTIFS('Test Case Register'!B5:B700,"AMC Contract",'Test Case Register'!C5:C700,"Cross-DocType Integration",'Test Case Register'!G5:G700,"Fail") -> 0 | F35: =COUNTIFS('Test Case Register'!B5:B700,"AMC Contract",'Test Case Register'!C5:C700,"Cross-DocType Integration",'Test Case Register'!G5:G700,"Blocked") -> 0 | G35: =IF(D35+E35=0,"-",D35/(D35+E35)) -> -
A36: Vendor Creation & Basic Details | B36: Vendor | C36: 4 | D36: =COUNTIFS('Test Case Register'!B5:B700,"Vendor",'Test Case Register'!C5:C700,"Vendor Creation & Basic Details",'Test Case Register'!G5:G700,"Pass") -> 0 | E36: =COUNTIFS('Test Case Register'!B5:B700,"Vendor",'Test Case Register'!C5:C700,"Vendor Creation & Basic Details",'Test Case Register'!G5:G700,"Fail") -> 0 | F36: =COUNTIFS('Test Case Register'!B5:B700,"Vendor",'Test Case Register'!C5:C700,"Vendor Creation & Basic Details",'Test Case Register'!G5:G700,"Blocked") -> 0 | G36: =IF(D36+E36=0,"-",D36/(D36+E36)) -> -
A37: Primary Contact Details | B37: Vendor | C37: 5 | D37: =COUNTIFS('Test Case Register'!B5:B700,"Vendor",'Test Case Register'!C5:C700,"Primary Contact Details",'Test Case Register'!G5:G700,"Pass") -> 0 | E37: =COUNTIFS('Test Case Register'!B5:B700,"Vendor",'Test Case Register'!C5:C700,"Primary Contact Details",'Test Case Register'!G5:G700,"Fail") -> 0 | F37: =COUNTIFS('Test Case Register'!B5:B700,"Vendor",'Test Case Register'!C5:C700,"Primary Contact Details",'Test Case Register'!G5:G700,"Blocked") -> 0 | G37: =IF(D37+E37=0,"-",D37/(D37+E37)) -> -
A38: Tax Identification | B38: Vendor | C38: 4 | D38: =COUNTIFS('Test Case Register'!B5:B700,"Vendor",'Test Case Register'!C5:C700,"Tax Identification",'Test Case Register'!G5:G700,"Pass") -> 0 | E38: =COUNTIFS('Test Case Register'!B5:B700,"Vendor",'Test Case Register'!C5:C700,"Tax Identification",'Test Case Register'!G5:G700,"Fail") -> 0 | F38: =COUNTIFS('Test Case Register'!B5:B700,"Vendor",'Test Case Register'!C5:C700,"Tax Identification",'Test Case Register'!G5:G700,"Blocked") -> 0 | G38: =IF(D38+E38=0,"-",D38/(D38+E38)) -> -
A39: Registered Address | B39: Vendor | C39: 3 | D39: =COUNTIFS('Test Case Register'!B5:B700,"Vendor",'Test Case Register'!C5:C700,"Registered Address",'Test Case Register'!G5:G700,"Pass") -> 0 | E39: =COUNTIFS('Test Case Register'!B5:B700,"Vendor",'Test Case Register'!C5:C700,"Registered Address",'Test Case Register'!G5:G700,"Fail") -> 0 | F39: =COUNTIFS('Test Case Register'!B5:B700,"Vendor",'Test Case Register'!C5:C700,"Registered Address",'Test Case Register'!G5:G700,"Blocked") -> 0 | G39: =IF(D39+E39=0,"-",D39/(D39+E39)) -> -
A40: Address Table | B40: Vendor | C40: 10 | D40: =COUNTIFS('Test Case Register'!B5:B700,"Vendor",'Test Case Register'!C5:C700,"Address Table",'Test Case Register'!G5:G700,"Pass") -> 0 | E40: =COUNTIFS('Test Case Register'!B5:B700,"Vendor",'Test Case Register'!C5:C700,"Address Table",'Test Case Register'!G5:G700,"Fail") -> 0 | F40: =COUNTIFS('Test Case Register'!B5:B700,"Vendor",'Test Case Register'!C5:C700,"Address Table",'Test Case Register'!G5:G700,"Blocked") -> 0 | G40: =IF(D40+E40=0,"-",D40/(D40+E40)) -> -
A41: Data Validation | B41: Vendor | C41: 4 | D41: =COUNTIFS('Test Case Register'!B5:B700,"Vendor",'Test Case Register'!C5:C700,"Data Validation",'Test Case Register'!G5:G700,"Pass") -> 0 | E41: =COUNTIFS('Test Case Register'!B5:B700,"Vendor",'Test Case Register'!C5:C700,"Data Validation",'Test Case Register'!G5:G700,"Fail") -> 0 | F41: =COUNTIFS('Test Case Register'!B5:B700,"Vendor",'Test Case Register'!C5:C700,"Data Validation",'Test Case Register'!G5:G700,"Blocked") -> 0 | G41: =IF(D41+E41=0,"-",D41/(D41+E41)) -> -
A42: Editing & Updates | B42: Vendor | C42: 5 | D42: =COUNTIFS('Test Case Register'!B5:B700,"Vendor",'Test Case Register'!C5:C700,"Editing & Updates",'Test Case Register'!G5:G700,"Pass") -> 0 | E42: =COUNTIFS('Test Case Register'!B5:B700,"Vendor",'Test Case Register'!C5:C700,"Editing & Updates",'Test Case Register'!G5:G700,"Fail") -> 0 | F42: =COUNTIFS('Test Case Register'!B5:B700,"Vendor",'Test Case Register'!C5:C700,"Editing & Updates",'Test Case Register'!G5:G700,"Blocked") -> 0 | G42: =IF(D42+E42=0,"-",D42/(D42+E42)) -> -
A43: Form Actions | B43: Vendor | C43: 5 | D43: =COUNTIFS('Test Case Register'!B5:B700,"Vendor",'Test Case Register'!C5:C700,"Form Actions",'Test Case Register'!G5:G700,"Pass") -> 0 | E43: =COUNTIFS('Test Case Register'!B5:B700,"Vendor",'Test Case Register'!C5:C700,"Form Actions",'Test Case Register'!G5:G700,"Fail") -> 0 | F43: =COUNTIFS('Test Case Register'!B5:B700,"Vendor",'Test Case Register'!C5:C700,"Form Actions",'Test Case Register'!G5:G700,"Blocked") -> 0 | G43: =IF(D43+E43=0,"-",D43/(D43+E43)) -> -
A44: Attendance Creation & Basic Details | B44: Attendance | C44: 6 | D44: =COUNTIFS('Test Case Register'!B5:B700,"Attendance",'Test Case Register'!C5:C700,"Attendance Creation & Basic Details",'Test Case Register'!G5:G700,"Pass") -> 0 | E44: =COUNTIFS('Test Case Register'!B5:B700,"Attendance",'Test Case Register'!C5:C700,"Attendance Creation & Basic Details",'Test Case Register'!G5:G700,"Fail") -> 0 | F44: =COUNTIFS('Test Case Register'!B5:B700,"Attendance",'Test Case Register'!C5:C700,"Attendance Creation & Basic Details",'Test Case Register'!G5:G700,"Blocked") -> 0 | G44: =IF(D44+E44=0,"-",D44/(D44+E44)) -> -
A45: Series & Auto-generation | B45: Attendance | C45: 3 | D45: =COUNTIFS('Test Case Register'!B5:B700,"Attendance",'Test Case Register'!C5:C700,"Series & Auto-generation",'Test Case Register'!G5:G700,"Pass") -> 0 | E45: =COUNTIFS('Test Case Register'!B5:B700,"Attendance",'Test Case Register'!C5:C700,"Series & Auto-generation",'Test Case Register'!G5:G700,"Fail") -> 0 | F45: =COUNTIFS('Test Case Register'!B5:B700,"Attendance",'Test Case Register'!C5:C700,"Series & Auto-generation",'Test Case Register'!G5:G700,"Blocked") -> 0 | G45: =IF(D45+E45=0,"-",D45/(D45+E45)) -> -
A46: Employee Selection | B46: Attendance | C46: 4 | D46: =COUNTIFS('Test Case Register'!B5:B700,"Attendance",'Test Case Register'!C5:C700,"Employee Selection",'Test Case Register'!G5:G700,"Pass") -> 0 | E46: =COUNTIFS('Test Case Register'!B5:B700,"Attendance",'Test Case Register'!C5:C700,"Employee Selection",'Test Case Register'!G5:G700,"Fail") -> 0 | F46: =COUNTIFS('Test Case Register'!B5:B700,"Attendance",'Test Case Register'!C5:C700,"Employee Selection",'Test Case Register'!G5:G700,"Blocked") -> 0 | G46: =IF(D46+E46=0,"-",D46/(D46+E46)) -> -
A47: Attendance Date | B47: Attendance | C47: 5 | D47: =COUNTIFS('Test Case Register'!B5:B700,"Attendance",'Test Case Register'!C5:C700,"Attendance Date",'Test Case Register'!G5:G700,"Pass") -> 0 | E47: =COUNTIFS('Test Case Register'!B5:B700,"Attendance",'Test Case Register'!C5:C700,"Attendance Date",'Test Case Register'!G5:G700,"Fail") -> 0 | F47: =COUNTIFS('Test Case Register'!B5:B700,"Attendance",'Test Case Register'!C5:C700,"Attendance Date",'Test Case Register'!G5:G700,"Blocked") -> 0 | G47: =IF(D47+E47=0,"-",D47/(D47+E47)) -> -
A48: Status Management | B48: Attendance | C48: 3 | D48: =COUNTIFS('Test Case Register'!B5:B700,"Attendance",'Test Case Register'!C5:C700,"Status Management",'Test Case Register'!G5:G700,"Pass") -> 0 | E48: =COUNTIFS('Test Case Register'!B5:B700,"Attendance",'Test Case Register'!C5:C700,"Status Management",'Test Case Register'!G5:G700,"Fail") -> 0 | F48: =COUNTIFS('Test Case Register'!B5:B700,"Attendance",'Test Case Register'!C5:C700,"Status Management",'Test Case Register'!G5:G700,"Blocked") -> 0 | G48: =IF(D48+E48=0,"-",D48/(D48+E48)) -> -
A49: Company Assignment | B49: Attendance | C49: 3 | D49: =COUNTIFS('Test Case Register'!B5:B700,"Attendance",'Test Case Register'!C5:C700,"Company Assignment",'Test Case Register'!G5:G700,"Pass") -> 0 | E49: =COUNTIFS('Test Case Register'!B5:B700,"Attendance",'Test Case Register'!C5:C700,"Company Assignment",'Test Case Register'!G5:G700,"Fail") -> 0 | F49: =COUNTIFS('Test Case Register'!B5:B700,"Attendance",'Test Case Register'!C5:C700,"Company Assignment",'Test Case Register'!G5:G700,"Blocked") -> 0 | G49: =IF(D49+E49=0,"-",D49/(D49+E49)) -> -
A50: Shift Details | B50: Attendance | C50: 4 | D50: =COUNTIFS('Test Case Register'!B5:B700,"Attendance",'Test Case Register'!C5:C700,"Shift Details",'Test Case Register'!G5:G700,"Pass") -> 0 | E50: =COUNTIFS('Test Case Register'!B5:B700,"Attendance",'Test Case Register'!C5:C700,"Shift Details",'Test Case Register'!G5:G700,"Fail") -> 0 | F50: =COUNTIFS('Test Case Register'!B5:B700,"Attendance",'Test Case Register'!C5:C700,"Shift Details",'Test Case Register'!G5:G700,"Blocked") -> 0 | G50: =IF(D50+E50=0,"-",D50/(D50+E50)) -> -
A51: Late Entry Tracking | B51: Attendance | C51: 5 | D51: =COUNTIFS('Test Case Register'!B5:B700,"Attendance",'Test Case Register'!C5:C700,"Late Entry Tracking",'Test Case Register'!G5:G700,"Pass") -> 0 | E51: =COUNTIFS('Test Case Register'!B5:B700,"Attendance",'Test Case Register'!C5:C700,"Late Entry Tracking",'Test Case Register'!G5:G700,"Fail") -> 0 | F51: =COUNTIFS('Test Case Register'!B5:B700,"Attendance",'Test Case Register'!C5:C700,"Late Entry Tracking",'Test Case Register'!G5:G700,"Blocked") -> 0 | G51: =IF(D51+E51=0,"-",D51/(D51+E51)) -> -
A52: Early Exit Tracking | B52: Attendance | C52: 5 | D52: =COUNTIFS('Test Case Register'!B5:B700,"Attendance",'Test Case Register'!C5:C700,"Early Exit Tracking",'Test Case Register'!G5:G700,"Pass") -> 0 | E52: =COUNTIFS('Test Case Register'!B5:B700,"Attendance",'Test Case Register'!C5:C700,"Early Exit Tracking",'Test Case Register'!G5:G700,"Fail") -> 0 | F52: =COUNTIFS('Test Case Register'!B5:B700,"Attendance",'Test Case Register'!C5:C700,"Early Exit Tracking",'Test Case Register'!G5:G700,"Blocked") -> 0 | G52: =IF(D52+E52=0,"-",D52/(D52+E52)) -> -
A53: Late Entry & Early Exit Combination | B53: Attendance | C53: 2 | D53: =COUNTIFS('Test Case Register'!B5:B700,"Attendance",'Test Case Register'!C5:C700,"Late Entry & Early Exit Combination",'Test Case Register'!G5:G700,"Pass") -> 0 | E53: =COUNTIFS('Test Case Register'!B5:B700,"Attendance",'Test Case Register'!C5:C700,"Late Entry & Early Exit Combination",'Test Case Register'!G5:G700,"Fail") -> 0 | F53: =COUNTIFS('Test Case Register'!B5:B700,"Attendance",'Test Case Register'!C5:C700,"Late Entry & Early Exit Combination",'Test Case Register'!G5:G700,"Blocked") -> 0 | G53: =IF(D53+E53=0,"-",D53/(D53+E53)) -> -
A54: Data Validation | B54: Attendance | C54: 3 | D54: =COUNTIFS('Test Case Register'!B5:B700,"Attendance",'Test Case Register'!C5:C700,"Data Validation",'Test Case Register'!G5:G700,"Pass") -> 0 | E54: =COUNTIFS('Test Case Register'!B5:B700,"Attendance",'Test Case Register'!C5:C700,"Data Validation",'Test Case Register'!G5:G700,"Fail") -> 0 | F54: =COUNTIFS('Test Case Register'!B5:B700,"Attendance",'Test Case Register'!C5:C700,"Data Validation",'Test Case Register'!G5:G700,"Blocked") -> 0 | G54: =IF(D54+E54=0,"-",D54/(D54+E54)) -> -
A55: Editing & Updates | B55: Attendance | C55: 6 | D55: =COUNTIFS('Test Case Register'!B5:B700,"Attendance",'Test Case Register'!C5:C700,"Editing & Updates",'Test Case Register'!G5:G700,"Pass") -> 0 | E55: =COUNTIFS('Test Case Register'!B5:B700,"Attendance",'Test Case Register'!C5:C700,"Editing & Updates",'Test Case Register'!G5:G700,"Fail") -> 0 | F55: =COUNTIFS('Test Case Register'!B5:B700,"Attendance",'Test Case Register'!C5:C700,"Editing & Updates",'Test Case Register'!G5:G700,"Blocked") -> 0 | G55: =IF(D55+E55=0,"-",D55/(D55+E55)) -> -
A56: Form Actions | B56: Attendance | C56: 3 | D56: =COUNTIFS('Test Case Register'!B5:B700,"Attendance",'Test Case Register'!C5:C700,"Form Actions",'Test Case Register'!G5:G700,"Pass") -> 0 | E56: =COUNTIFS('Test Case Register'!B5:B700,"Attendance",'Test Case Register'!C5:C700,"Form Actions",'Test Case Register'!G5:G700,"Fail") -> 0 | F56: =COUNTIFS('Test Case Register'!B5:B700,"Attendance",'Test Case Register'!C5:C700,"Form Actions",'Test Case Register'!G5:G700,"Blocked") -> 0 | G56: =IF(D56+E56=0,"-",D56/(D56+E56)) -> -
A57: Expense Claim Creation & Basic Details | B57: Expense Claim | C57: 2 | D57: =COUNTIFS('Test Case Register'!B5:B700,"Expense Claim",'Test Case Register'!C5:C700,"Expense Claim Creation & Basic Details",'Test Case Register'!G5:G700,"Pass") -> 0 | E57: =COUNTIFS('Test Case Register'!B5:B700,"Expense Claim",'Test Case Register'!C5:C700,"Expense Claim Creation & Basic Details",'Test Case Register'!G5:G700,"Fail") -> 0 | F57: =COUNTIFS('Test Case Register'!B5:B700,"Expense Claim",'Test Case Register'!C5:C700,"Expense Claim Creation & Basic Details",'Test Case Register'!G5:G700,"Blocked") -> 0 | G57: =IF(D57+E57=0,"-",D57/(D57+E57)) -> -
A58: Series & Auto-generation | B58: Expense Claim | C58: 3 | D58: =COUNTIFS('Test Case Register'!B5:B700,"Expense Claim",'Test Case Register'!C5:C700,"Series & Auto-generation",'Test Case Register'!G5:G700,"Pass") -> 0 | E58: =COUNTIFS('Test Case Register'!B5:B700,"Expense Claim",'Test Case Register'!C5:C700,"Series & Auto-generation",'Test Case Register'!G5:G700,"Fail") -> 0 | F58: =COUNTIFS('Test Case Register'!B5:B700,"Expense Claim",'Test Case Register'!C5:C700,"Series & Auto-generation",'Test Case Register'!G5:G700,"Blocked") -> 0 | G58: =IF(D58+E58=0,"-",D58/(D58+E58)) -> -
A59: Employee Selection | B59: Expense Claim | C59: 4 | D59: =COUNTIFS('Test Case Register'!B5:B700,"Expense Claim",'Test Case Register'!C5:C700,"Employee Selection",'Test Case Register'!G5:G700,"Pass") -> 0 | E59: =COUNTIFS('Test Case Register'!B5:B700,"Expense Claim",'Test Case Register'!C5:C700,"Employee Selection",'Test Case Register'!G5:G700,"Fail") -> 0 | F59: =COUNTIFS('Test Case Register'!B5:B700,"Expense Claim",'Test Case Register'!C5:C700,"Employee Selection",'Test Case Register'!G5:G700,"Blocked") -> 0 | G59: =IF(D59+E59=0,"-",D59/(D59+E59)) -> -
A60: Company Details | B60: Expense Claim | C60: 4 | D60: =COUNTIFS('Test Case Register'!B5:B700,"Expense Claim",'Test Case Register'!C5:C700,"Company Details",'Test Case Register'!G5:G700,"Pass") -> 0 | E60: =COUNTIFS('Test Case Register'!B5:B700,"Expense Claim",'Test Case Register'!C5:C700,"Company Details",'Test Case Register'!G5:G700,"Fail") -> 0 | F60: =COUNTIFS('Test Case Register'!B5:B700,"Expense Claim",'Test Case Register'!C5:C700,"Company Details",'Test Case Register'!G5:G700,"Blocked") -> 0 | G60: =IF(D60+E60=0,"-",D60/(D60+E60)) -> -
A61: Expense Approver | B61: Expense Claim | C61: 3 | D61: =COUNTIFS('Test Case Register'!B5:B700,"Expense Claim",'Test Case Register'!C5:C700,"Expense Approver",'Test Case Register'!G5:G700,"Pass") -> 0 | E61: =COUNTIFS('Test Case Register'!B5:B700,"Expense Claim",'Test Case Register'!C5:C700,"Expense Approver",'Test Case Register'!G5:G700,"Fail") -> 0 | F61: =COUNTIFS('Test Case Register'!B5:B700,"Expense Claim",'Test Case Register'!C5:C700,"Expense Approver",'Test Case Register'!G5:G700,"Blocked") -> 0 | G61: =IF(D61+E61=0,"-",D61/(D61+E61)) -> -
A62: Approval Status | B62: Expense Claim | C62: 4 | D62: =COUNTIFS('Test Case Register'!B5:B700,"Expense Claim",'Test Case Register'!C5:C700,"Approval Status",'Test Case Register'!G5:G700,"Pass") -> 0 | E62: =COUNTIFS('Test Case Register'!B5:B700,"Expense Claim",'Test Case Register'!C5:C700,"Approval Status",'Test Case Register'!G5:G700,"Fail") -> 0 | F62: =COUNTIFS('Test Case Register'!B5:B700,"Expense Claim",'Test Case Register'!C5:C700,"Approval Status",'Test Case Register'!G5:G700,"Blocked") -> 0 | G62: =IF(D62+E62=0,"-",D62/(D62+E62)) -> -
A63: Expenses Table | B63: Expense Claim | C63: 13 | D63: =COUNTIFS('Test Case Register'!B5:B700,"Expense Claim",'Test Case Register'!C5:C700,"Expenses Table",'Test Case Register'!G5:G700,"Pass") -> 0 | E63: =COUNTIFS('Test Case Register'!B5:B700,"Expense Claim",'Test Case Register'!C5:C700,"Expenses Table",'Test Case Register'!G5:G700,"Fail") -> 0 | F63: =COUNTIFS('Test Case Register'!B5:B700,"Expense Claim",'Test Case Register'!C5:C700,"Expenses Table",'Test Case Register'!G5:G700,"Blocked") -> 0 | G63: =IF(D63+E63=0,"-",D63/(D63+E63)) -> -
A64: Taxes & Charges | B64: Expense Claim | C64: 7 | D64: =COUNTIFS('Test Case Register'!B5:B700,"Expense Claim",'Test Case Register'!C5:C700,"Taxes & Charges",'Test Case Register'!G5:G700,"Pass") -> 0 | E64: =COUNTIFS('Test Case Register'!B5:B700,"Expense Claim",'Test Case Register'!C5:C700,"Taxes & Charges",'Test Case Register'!G5:G700,"Fail") -> 0 | F64: =COUNTIFS('Test Case Register'!B5:B700,"Expense Claim",'Test Case Register'!C5:C700,"Taxes & Charges",'Test Case Register'!G5:G700,"Blocked") -> 0 | G64: =IF(D64+E64=0,"-",D64/(D64+E64)) -> -
A65: Accounting Details | B65: Expense Claim | C65: 6 | D65: =COUNTIFS('Test Case Register'!B5:B700,"Expense Claim",'Test Case Register'!C5:C700,"Accounting Details",'Test Case Register'!G5:G700,"Pass") -> 0 | E65: =COUNTIFS('Test Case Register'!B5:B700,"Expense Claim",'Test Case Register'!C5:C700,"Accounting Details",'Test Case Register'!G5:G700,"Fail") -> 0 | F65: =COUNTIFS('Test Case Register'!B5:B700,"Expense Claim",'Test Case Register'!C5:C700,"Accounting Details",'Test Case Register'!G5:G700,"Blocked") -> 0 | G65: =IF(D65+E65=0,"-",D65/(D65+E65)) -> -
A66: Data Validation | B66: Expense Claim | C66: 4 | D66: =COUNTIFS('Test Case Register'!B5:B700,"Expense Claim",'Test Case Register'!C5:C700,"Data Validation",'Test Case Register'!G5:G700,"Pass") -> 0 | E66: =COUNTIFS('Test Case Register'!B5:B700,"Expense Claim",'Test Case Register'!C5:C700,"Data Validation",'Test Case Register'!G5:G700,"Fail") -> 0 | F66: =COUNTIFS('Test Case Register'!B5:B700,"Expense Claim",'Test Case Register'!C5:C700,"Data Validation",'Test Case Register'!G5:G700,"Blocked") -> 0 | G66: =IF(D66+E66=0,"-",D66/(D66+E66)) -> -
A67: Editing & Updates | B67: Expense Claim | C67: 4 | D67: =COUNTIFS('Test Case Register'!B5:B700,"Expense Claim",'Test Case Register'!C5:C700,"Editing & Updates",'Test Case Register'!G5:G700,"Pass") -> 0 | E67: =COUNTIFS('Test Case Register'!B5:B700,"Expense Claim",'Test Case Register'!C5:C700,"Editing & Updates",'Test Case Register'!G5:G700,"Fail") -> 0 | F67: =COUNTIFS('Test Case Register'!B5:B700,"Expense Claim",'Test Case Register'!C5:C700,"Editing & Updates",'Test Case Register'!G5:G700,"Blocked") -> 0 | G67: =IF(D67+E67=0,"-",D67/(D67+E67)) -> -
A68: Form Actions | B68: Expense Claim | C68: 6 | D68: =COUNTIFS('Test Case Register'!B5:B700,"Expense Claim",'Test Case Register'!C5:C700,"Form Actions",'Test Case Register'!G5:G700,"Pass") -> 0 | E68: =COUNTIFS('Test Case Register'!B5:B700,"Expense Claim",'Test Case Register'!C5:C700,"Form Actions",'Test Case Register'!G5:G700,"Fail") -> 0 | F68: =COUNTIFS('Test Case Register'!B5:B700,"Expense Claim",'Test Case Register'!C5:C700,"Form Actions",'Test Case Register'!G5:G700,"Blocked") -> 0 | G68: =IF(D68+E68=0,"-",D68/(D68+E68)) -> -
A69: Leave Application Creation & Basic Details | B69: Leave Application | C69: 2 | D69: =COUNTIFS('Test Case Register'!B5:B700,"Leave Application",'Test Case Register'!C5:C700,"Leave Application Creation & Basic Details",'Test Case Register'!G5:G700,"Pass") -> 0 | E69: =COUNTIFS('Test Case Register'!B5:B700,"Leave Application",'Test Case Register'!C5:C700,"Leave Application Creation & Basic Details",'Test Case Register'!G5:G700,"Fail") -> 0 | F69: =COUNTIFS('Test Case Register'!B5:B700,"Leave Application",'Test Case Register'!C5:C700,"Leave Application Creation & Basic Details",'Test Case Register'!G5:G700,"Blocked") -> 0 | G69: =IF(D69+E69=0,"-",D69/(D69+E69)) -> -
A70: Series & Auto-generation | B70: Leave Application | C70: 3 | D70: =COUNTIFS('Test Case Register'!B5:B700,"Leave Application",'Test Case Register'!C5:C700,"Series & Auto-generation",'Test Case Register'!G5:G700,"Pass") -> 0 | E70: =COUNTIFS('Test Case Register'!B5:B700,"Leave Application",'Test Case Register'!C5:C700,"Series & Auto-generation",'Test Case Register'!G5:G700,"Fail") -> 0 | F70: =COUNTIFS('Test Case Register'!B5:B700,"Leave Application",'Test Case Register'!C5:C700,"Series & Auto-generation",'Test Case Register'!G5:G700,"Blocked") -> 0 | G70: =IF(D70+E70=0,"-",D70/(D70+E70)) -> -
A71: Employee Selection | B71: Leave Application | C71: 3 | D71: =COUNTIFS('Test Case Register'!B5:B700,"Leave Application",'Test Case Register'!C5:C700,"Employee Selection",'Test Case Register'!G5:G700,"Pass") -> 0 | E71: =COUNTIFS('Test Case Register'!B5:B700,"Leave Application",'Test Case Register'!C5:C700,"Employee Selection",'Test Case Register'!G5:G700,"Fail") -> 0 | F71: =COUNTIFS('Test Case Register'!B5:B700,"Leave Application",'Test Case Register'!C5:C700,"Employee Selection",'Test Case Register'!G5:G700,"Blocked") -> 0 | G71: =IF(D71+E71=0,"-",D71/(D71+E71)) -> -
A72: Leave Type Selection | B72: Leave Application | C72: 4 | D72: =COUNTIFS('Test Case Register'!B5:B700,"Leave Application",'Test Case Register'!C5:C700,"Leave Type Selection",'Test Case Register'!G5:G700,"Pass") -> 0 | E72: =COUNTIFS('Test Case Register'!B5:B700,"Leave Application",'Test Case Register'!C5:C700,"Leave Type Selection",'Test Case Register'!G5:G700,"Fail") -> 0 | F72: =COUNTIFS('Test Case Register'!B5:B700,"Leave Application",'Test Case Register'!C5:C700,"Leave Type Selection",'Test Case Register'!G5:G700,"Blocked") -> 0 | G72: =IF(D72+E72=0,"-",D72/(D72+E72)) -> -
A73: Company Details | B73: Leave Application | C73: 3 | D73: =COUNTIFS('Test Case Register'!B5:B700,"Leave Application",'Test Case Register'!C5:C700,"Company Details",'Test Case Register'!G5:G700,"Pass") -> 0 | E73: =COUNTIFS('Test Case Register'!B5:B700,"Leave Application",'Test Case Register'!C5:C700,"Company Details",'Test Case Register'!G5:G700,"Fail") -> 0 | F73: =COUNTIFS('Test Case Register'!B5:B700,"Leave Application",'Test Case Register'!C5:C700,"Company Details",'Test Case Register'!G5:G700,"Blocked") -> 0 | G73: =IF(D73+E73=0,"-",D73/(D73+E73)) -> -
A74: Date Range | B74: Leave Application | C74: 7 | D74: =COUNTIFS('Test Case Register'!B5:B700,"Leave Application",'Test Case Register'!C5:C700,"Date Range",'Test Case Register'!G5:G700,"Pass") -> 0 | E74: =COUNTIFS('Test Case Register'!B5:B700,"Leave Application",'Test Case Register'!C5:C700,"Date Range",'Test Case Register'!G5:G700,"Fail") -> 0 | F74: =COUNTIFS('Test Case Register'!B5:B700,"Leave Application",'Test Case Register'!C5:C700,"Date Range",'Test Case Register'!G5:G700,"Blocked") -> 0 | G74: =IF(D74+E74=0,"-",D74/(D74+E74)) -> -
A75: Half Day Leave | B75: Leave Application | C75: 6 | D75: =COUNTIFS('Test Case Register'!B5:B700,"Leave Application",'Test Case Register'!C5:C700,"Half Day Leave",'Test Case Register'!G5:G700,"Pass") -> 0 | E75: =COUNTIFS('Test Case Register'!B5:B700,"Leave Application",'Test Case Register'!C5:C700,"Half Day Leave",'Test Case Register'!G5:G700,"Fail") -> 0 | F75: =COUNTIFS('Test Case Register'!B5:B700,"Leave Application",'Test Case Register'!C5:C700,"Half Day Leave",'Test Case Register'!G5:G700,"Blocked") -> 0 | G75: =IF(D75+E75=0,"-",D75/(D75+E75)) -> -
A76: Reason | B76: Leave Application | C76: 3 | D76: =COUNTIFS('Test Case Register'!B5:B700,"Leave Application",'Test Case Register'!C5:C700,"Reason",'Test Case Register'!G5:G700,"Pass") -> 0 | E76: =COUNTIFS('Test Case Register'!B5:B700,"Leave Application",'Test Case Register'!C5:C700,"Reason",'Test Case Register'!G5:G700,"Fail") -> 0 | F76: =COUNTIFS('Test Case Register'!B5:B700,"Leave Application",'Test Case Register'!C5:C700,"Reason",'Test Case Register'!G5:G700,"Blocked") -> 0 | G76: =IF(D76+E76=0,"-",D76/(D76+E76)) -> -
A77: Leave Approver | B77: Leave Application | C77: 4 | D77: =COUNTIFS('Test Case Register'!B5:B700,"Leave Application",'Test Case Register'!C5:C700,"Leave Approver",'Test Case Register'!G5:G700,"Pass") -> 0 | E77: =COUNTIFS('Test Case Register'!B5:B700,"Leave Application",'Test Case Register'!C5:C700,"Leave Approver",'Test Case Register'!G5:G700,"Fail") -> 0 | F77: =COUNTIFS('Test Case Register'!B5:B700,"Leave Application",'Test Case Register'!C5:C700,"Leave Approver",'Test Case Register'!G5:G700,"Blocked") -> 0 | G77: =IF(D77+E77=0,"-",D77/(D77+E77)) -> -
A78: Posting Date | B78: Leave Application | C78: 3 | D78: =COUNTIFS('Test Case Register'!B5:B700,"Leave Application",'Test Case Register'!C5:C700,"Posting Date",'Test Case Register'!G5:G700,"Pass") -> 0 | E78: =COUNTIFS('Test Case Register'!B5:B700,"Leave Application",'Test Case Register'!C5:C700,"Posting Date",'Test Case Register'!G5:G700,"Fail") -> 0 | F78: =COUNTIFS('Test Case Register'!B5:B700,"Leave Application",'Test Case Register'!C5:C700,"Posting Date",'Test Case Register'!G5:G700,"Blocked") -> 0 | G78: =IF(D78+E78=0,"-",D78/(D78+E78)) -> -
A79: Leave Balance | B79: Leave Application | C79: 5 | D79: =COUNTIFS('Test Case Register'!B5:B700,"Leave Application",'Test Case Register'!C5:C700,"Leave Balance",'Test Case Register'!G5:G700,"Pass") -> 0 | E79: =COUNTIFS('Test Case Register'!B5:B700,"Leave Application",'Test Case Register'!C5:C700,"Leave Balance",'Test Case Register'!G5:G700,"Fail") -> 0 | F79: =COUNTIFS('Test Case Register'!B5:B700,"Leave Application",'Test Case Register'!C5:C700,"Leave Balance",'Test Case Register'!G5:G700,"Blocked") -> 0 | G79: =IF(D79+E79=0,"-",D79/(D79+E79)) -> -
A80: Status & Workflow | B80: Leave Application | C80: 5 | D80: =COUNTIFS('Test Case Register'!B5:B700,"Leave Application",'Test Case Register'!C5:C700,"Status & Workflow",'Test Case Register'!G5:G700,"Pass") -> 0 | E80: =COUNTIFS('Test Case Register'!B5:B700,"Leave Application",'Test Case Register'!C5:C700,"Status & Workflow",'Test Case Register'!G5:G700,"Fail") -> 0 | F80: =COUNTIFS('Test Case Register'!B5:B700,"Leave Application",'Test Case Register'!C5:C700,"Status & Workflow",'Test Case Register'!G5:G700,"Blocked") -> 0 | G80: =IF(D80+E80=0,"-",D80/(D80+E80)) -> -
A81: Data Validation | B81: Leave Application | C81: 5 | D81: =COUNTIFS('Test Case Register'!B5:B700,"Leave Application",'Test Case Register'!C5:C700,"Data Validation",'Test Case Register'!G5:G700,"Pass") -> 0 | E81: =COUNTIFS('Test Case Register'!B5:B700,"Leave Application",'Test Case Register'!C5:C700,"Data Validation",'Test Case Register'!G5:G700,"Fail") -> 0 | F81: =COUNTIFS('Test Case Register'!B5:B700,"Leave Application",'Test Case Register'!C5:C700,"Data Validation",'Test Case Register'!G5:G700,"Blocked") -> 0 | G81: =IF(D81+E81=0,"-",D81/(D81+E81)) -> -
A82: Editing & Updates | B82: Leave Application | C82: 5 | D82: =COUNTIFS('Test Case Register'!B5:B700,"Leave Application",'Test Case Register'!C5:C700,"Editing & Updates",'Test Case Register'!G5:G700,"Pass") -> 0 | E82: =COUNTIFS('Test Case Register'!B5:B700,"Leave Application",'Test Case Register'!C5:C700,"Editing & Updates",'Test Case Register'!G5:G700,"Fail") -> 0 | F82: =COUNTIFS('Test Case Register'!B5:B700,"Leave Application",'Test Case Register'!C5:C700,"Editing & Updates",'Test Case Register'!G5:G700,"Blocked") -> 0 | G82: =IF(D82+E82=0,"-",D82/(D82+E82)) -> -
A83: Form Actions | B83: Leave Application | C83: 7 | D83: =COUNTIFS('Test Case Register'!B5:B700,"Leave Application",'Test Case Register'!C5:C700,"Form Actions",'Test Case Register'!G5:G700,"Pass") -> 0 | E83: =COUNTIFS('Test Case Register'!B5:B700,"Leave Application",'Test Case Register'!C5:C700,"Form Actions",'Test Case Register'!G5:G700,"Fail") -> 0 | F83: =COUNTIFS('Test Case Register'!B5:B700,"Leave Application",'Test Case Register'!C5:C700,"Form Actions",'Test Case Register'!G5:G700,"Blocked") -> 0 | G83: =IF(D83+E83=0,"-",D83/(D83+E83)) -> -
A84: Service Call Creation & Basic Details | B84: Service Call | C84: 5 | D84: =COUNTIFS('Test Case Register'!B5:B700,"Service Call",'Test Case Register'!C5:C700,"Service Call Creation & Basic Details",'Test Case Register'!G5:G700,"Pass") -> 0 | E84: =COUNTIFS('Test Case Register'!B5:B700,"Service Call",'Test Case Register'!C5:C700,"Service Call Creation & Basic Details",'Test Case Register'!G5:G700,"Fail") -> 0 | F84: =COUNTIFS('Test Case Register'!B5:B700,"Service Call",'Test Case Register'!C5:C700,"Service Call Creation & Basic Details",'Test Case Register'!G5:G700,"Blocked") -> 0 | G84: =IF(D84+E84=0,"-",D84/(D84+E84)) -> -
A85: Customer & Location Validation | B85: Service Call | C85: 4 | D85: =COUNTIFS('Test Case Register'!B5:B700,"Service Call",'Test Case Register'!C5:C700,"Customer & Location Validation",'Test Case Register'!G5:G700,"Pass") -> 0 | E85: =COUNTIFS('Test Case Register'!B5:B700,"Service Call",'Test Case Register'!C5:C700,"Customer & Location Validation",'Test Case Register'!G5:G700,"Fail") -> 0 | F85: =COUNTIFS('Test Case Register'!B5:B700,"Service Call",'Test Case Register'!C5:C700,"Customer & Location Validation",'Test Case Register'!G5:G700,"Blocked") -> 0 | G85: =IF(D85+E85=0,"-",D85/(D85+E85)) -> -
A86: Technician Assignment | B86: Service Call | C86: 4 | D86: =COUNTIFS('Test Case Register'!B5:B700,"Service Call",'Test Case Register'!C5:C700,"Technician Assignment",'Test Case Register'!G5:G700,"Pass") -> 0 | E86: =COUNTIFS('Test Case Register'!B5:B700,"Service Call",'Test Case Register'!C5:C700,"Technician Assignment",'Test Case Register'!G5:G700,"Fail") -> 0 | F86: =COUNTIFS('Test Case Register'!B5:B700,"Service Call",'Test Case Register'!C5:C700,"Technician Assignment",'Test Case Register'!G5:G700,"Blocked") -> 0 | G86: =IF(D86+E86=0,"-",D86/(D86+E86)) -> -
A87: Priority & Status Management | B87: Service Call | C87: 5 | D87: =COUNTIFS('Test Case Register'!B5:B700,"Service Call",'Test Case Register'!C5:C700,"Priority & Status Management",'Test Case Register'!G5:G700,"Pass") -> 0 | E87: =COUNTIFS('Test Case Register'!B5:B700,"Service Call",'Test Case Register'!C5:C700,"Priority & Status Management",'Test Case Register'!G5:G700,"Fail") -> 0 | F87: =COUNTIFS('Test Case Register'!B5:B700,"Service Call",'Test Case Register'!C5:C700,"Priority & Status Management",'Test Case Register'!G5:G700,"Blocked") -> 0 | G87: =IF(D87+E87=0,"-",D87/(D87+E87)) -> -
A88: Service Date & Time | B88: Service Call | C88: 4 | D88: =COUNTIFS('Test Case Register'!B5:B700,"Service Call",'Test Case Register'!C5:C700,"Service Date & Time",'Test Case Register'!G5:G700,"Pass") -> 0 | E88: =COUNTIFS('Test Case Register'!B5:B700,"Service Call",'Test Case Register'!C5:C700,"Service Date & Time",'Test Case Register'!G5:G700,"Fail") -> 0 | F88: =COUNTIFS('Test Case Register'!B5:B700,"Service Call",'Test Case Register'!C5:C700,"Service Date & Time",'Test Case Register'!G5:G700,"Blocked") -> 0 | G88: =IF(D88+E88=0,"-",D88/(D88+E88)) -> -
A89: Service Items & Inventory | B89: Service Call | C89: 5 | D89: =COUNTIFS('Test Case Register'!B5:B700,"Service Call",'Test Case Register'!C5:C700,"Service Items & Inventory",'Test Case Register'!G5:G700,"Pass") -> 0 | E89: =COUNTIFS('Test Case Register'!B5:B700,"Service Call",'Test Case Register'!C5:C700,"Service Items & Inventory",'Test Case Register'!G5:G700,"Fail") -> 0 | F89: =COUNTIFS('Test Case Register'!B5:B700,"Service Call",'Test Case Register'!C5:C700,"Service Items & Inventory",'Test Case Register'!G5:G700,"Blocked") -> 0 | G89: =IF(D89+E89=0,"-",D89/(D89+E89)) -> -
A90: Billing & Cost Calculation | B90: Service Call | C90: 4 | D90: =COUNTIFS('Test Case Register'!B5:B700,"Service Call",'Test Case Register'!C5:C700,"Billing & Cost Calculation",'Test Case Register'!G5:G700,"Pass") -> 0 | E90: =COUNTIFS('Test Case Register'!B5:B700,"Service Call",'Test Case Register'!C5:C700,"Billing & Cost Calculation",'Test Case Register'!G5:G700,"Fail") -> 0 | F90: =COUNTIFS('Test Case Register'!B5:B700,"Service Call",'Test Case Register'!C5:C700,"Billing & Cost Calculation",'Test Case Register'!G5:G700,"Blocked") -> 0 | G90: =IF(D90+E90=0,"-",D90/(D90+E90)) -> -
A91: SLA & Warranty | B91: Service Call | C91: 3 | D91: =COUNTIFS('Test Case Register'!B5:B700,"Service Call",'Test Case Register'!C5:C700,"SLA & Warranty",'Test Case Register'!G5:G700,"Pass") -> 0 | E91: =COUNTIFS('Test Case Register'!B5:B700,"Service Call",'Test Case Register'!C5:C700,"SLA & Warranty",'Test Case Register'!G5:G700,"Fail") -> 0 | F91: =COUNTIFS('Test Case Register'!B5:B700,"Service Call",'Test Case Register'!C5:C700,"SLA & Warranty",'Test Case Register'!G5:G700,"Blocked") -> 0 | G91: =IF(D91+E91=0,"-",D91/(D91+E91)) -> -
A92: Documentation | B92: Service Call | C92: 4 | D92: =COUNTIFS('Test Case Register'!B5:B700,"Service Call",'Test Case Register'!C5:C700,"Documentation",'Test Case Register'!G5:G700,"Pass") -> 0 | E92: =COUNTIFS('Test Case Register'!B5:B700,"Service Call",'Test Case Register'!C5:C700,"Documentation",'Test Case Register'!G5:G700,"Fail") -> 0 | F92: =COUNTIFS('Test Case Register'!B5:B700,"Service Call",'Test Case Register'!C5:C700,"Documentation",'Test Case Register'!G5:G700,"Blocked") -> 0 | G92: =IF(D92+E92=0,"-",D92/(D92+E92)) -> -
A93: Data Validation | B93: Service Call | C93: 3 | D93: =COUNTIFS('Test Case Register'!B5:B700,"Service Call",'Test Case Register'!C5:C700,"Data Validation",'Test Case Register'!G5:G700,"Pass") -> 0 | E93: =COUNTIFS('Test Case Register'!B5:B700,"Service Call",'Test Case Register'!C5:C700,"Data Validation",'Test Case Register'!G5:G700,"Fail") -> 0 | F93: =COUNTIFS('Test Case Register'!B5:B700,"Service Call",'Test Case Register'!C5:C700,"Data Validation",'Test Case Register'!G5:G700,"Blocked") -> 0 | G93: =IF(D93+E93=0,"-",D93/(D93+E93)) -> -
A94: Editing & Updates | B94: Service Call | C94: 3 | D94: =COUNTIFS('Test Case Register'!B5:B700,"Service Call",'Test Case Register'!C5:C700,"Editing & Updates",'Test Case Register'!G5:G700,"Pass") -> 0 | E94: =COUNTIFS('Test Case Register'!B5:B700,"Service Call",'Test Case Register'!C5:C700,"Editing & Updates",'Test Case Register'!G5:G700,"Fail") -> 0 | F94: =COUNTIFS('Test Case Register'!B5:B700,"Service Call",'Test Case Register'!C5:C700,"Editing & Updates",'Test Case Register'!G5:G700,"Blocked") -> 0 | G94: =IF(D94+E94=0,"-",D94/(D94+E94)) -> -
A95: Bulk Operations | B95: Service Call | C95: 3 | D95: =COUNTIFS('Test Case Register'!B5:B700,"Service Call",'Test Case Register'!C5:C700,"Bulk Operations",'Test Case Register'!G5:G700,"Pass") -> 0 | E95: =COUNTIFS('Test Case Register'!B5:B700,"Service Call",'Test Case Register'!C5:C700,"Bulk Operations",'Test Case Register'!G5:G700,"Fail") -> 0 | F95: =COUNTIFS('Test Case Register'!B5:B700,"Service Call",'Test Case Register'!C5:C700,"Bulk Operations",'Test Case Register'!G5:G700,"Blocked") -> 0 | G95: =IF(D95+E95=0,"-",D95/(D95+E95)) -> -
A96: Permissions & Access | B96: Service Call | C96: 3 | D96: =COUNTIFS('Test Case Register'!B5:B700,"Service Call",'Test Case Register'!C5:C700,"Permissions & Access",'Test Case Register'!G5:G700,"Pass") -> 0 | E96: =COUNTIFS('Test Case Register'!B5:B700,"Service Call",'Test Case Register'!C5:C700,"Permissions & Access",'Test Case Register'!G5:G700,"Fail") -> 0 | F96: =COUNTIFS('Test Case Register'!B5:B700,"Service Call",'Test Case Register'!C5:C700,"Permissions & Access",'Test Case Register'!G5:G700,"Blocked") -> 0 | G96: =IF(D96+E96=0,"-",D96/(D96+E96)) -> -

Sheet Priority Analysis
A1: AMC Core — Master Priority & Coverage Analysis
A2: All 320 test cases sorted by priority. Execute Critical first across all DocTypes.
A4: Priority | B4: Test ID | C4: DocType | D4: Module | E4: Test Case Title | F4: Business Rule
A5: Critical | B5: CUST-001 | C5: AMC Customers | D5: Customer Creation & Basic Details | E5: Create customer with Customer Name only (minimum required) | F5: BR-CUST-01
A6: Critical | B6: CUST-002 | C6: AMC Customers | D6: Customer Creation & Basic Details | E6: Create Company customer with all basic fields (Name, Type, GST, PAN) | F6: BR-CUST-01, BR-CUST-02
A7: Critical | B7: CUST-005 | C7: AMC Customers | D7: GST Validation | E7: Valid 15-character GSTIN is accepted | F7: BR-CUST-03
A8: Critical | B8: CUST-006 | C8: AMC Customers | D8: GST Validation | E8: Invalid GST format is rejected with specific error message | F8: BR-CUST-03
A9: Critical | B9: CUST-007 | C9: AMC Customers | D9: GST Validation | E9: Duplicate GSTIN across two customers is blocked | F9: BR-CUST-04
A10: Critical | B10: CUST-010 | C10: AMC Customers | D10: Branch Locations | E10: Add single branch location to customer | F10: BR-CUST-06
A11: Critical | B11: CUST-014 | C11: AMC Customers | D11: Contact Details | E11: Add primary contact to customer | F11: BR-CUST-07
A12: Critical | B12: CUST-020 | C12: AMC Customers | D12: Permissions | E12: Technician role can only READ AMC Customers | F12: BR-CUST-11
A13: Critical | B13: CON-001 | C13: AMC Contract | D13: Contract Creation | E13: Create AMC Contract with all mandatory fields | F13: BR-CON-01
A14: Critical | B14: CON-002 | C14: AMC Contract | D14: Contract Creation | E14: Start Date is mandatory — save fails without it | F14: BR-CON-01
A15: Critical | B15: CON-003 | C15: AMC Contract | D15: Contract Creation | E15: End Date is mandatory — save fails without it | F15: BR-CON-01
... A324: Medium | B324: SC-038 | C324: Service Call | D324: Documentation | E324: Delete attached document from Service Call | F324: BR-SC-12
A327: Priority Summary
A328: Priority | B328: Count | C328: % of Total
A329: Critical | B329: 168 | C329: 0.525
A330: High | B330: 113 | C330: 0.353125
A331: Medium | B331: 39 | C331: 0.121875

Sheet Business Rules
A1: AMC Core — Master Business Rules Reference
A2: 98 business rules across 7 DocTypes. Every test case traces to exactly one rule.
A4: Rule ID | B4: DocType | C4: Category | D4: Rule Name | E4: Description / ERPNext v15 Field Details | F4: Test Cases
A5: ▌ AMC Customers
A6: BR-CUST-01 | B6: AMC Customers | C6: Creation | D6: Customer Name is primary identifier | E6: Customer Name is core searchable field. Naming series CUST-.####. auto-assigns ID. | F6: CUST-001, CUST-002
A7: BR-CUST-02 | B7: AMC Customers | C7: Creation | D7: Customer Type classifies legal entity | E7: Must be Company, Individual, or Partnership. Determines tax and contact rules. | F7: CUST-003, CUST-004
A8: BR-CUST-03 | B8: AMC Customers | C8: GST Validation | D8: GST must match 15-char regex or be blank | E8: Regex: ^$|^[0-9]{2}[A-Z]{4}[A-Z0-9]{1}[0-9]{4}[A-Z]{1}[1-9A-Z]{1}[A-Z]{1}[A-Z0-9]{1}$. Error message shown on mismatch. | F8: CUST-005, CUST-006, CUST-008
A9: BR-CUST-04 | B9: AMC Customers | C9: GST Validation | D9: GST is unique across all customers | E9: unique:1 on GST field. Two customers cannot share same GSTIN. | F9: CUST-007
A10: BR-CUST-05 | B10: AMC Customers | C10: PAN Validation | D10: PAN is unique across all customers | E10: unique:1 on PAN field. Two customers cannot share same PAN. | F10: CUST-009
A11: BR-CUST-06 | B11: AMC Customers | C11: Branches | D11: Branch Locations define service sites | E11: Customer Branch Mapping child table: Branch + Address. Branches link to Contracts. | F11: CUST-010, CUST-011, CUST-012, CUST-013
A12: BR-CUST-07 | B12: AMC Customers | C12: Contacts | D12: Contact Details store per-branch persons | E12: Customer Contact Mapping: Name, Mobile, Email, Branch, Is Primary. Drives contract contact selection. | F12: CUST-014, CUST-016, CUST-017
A13: BR-CUST-08 | B13: AMC Customers | C13: Contacts | D13: Only one Is Primary contact per customer | E13: Business rule: Is Primary uniqueness per customer to avoid escalation ambiguity. | F13: CUST-015
A14: BR-CUST-09 | B14: AMC Customers | C14: Connections | D14: Customer links to Contracts and Service Calls | E14: links[]: AMC Contract.customer + Service Call.customer. Visible in Connections tab HTML. | F14: CUST-018, CUST-019
A15: BR-CUST-10 | B15: AMC Customers | C15: Data Integrity | D15: Customer with active contracts cannot be deleted | E15: Referential integrity: deletion blocked if AMC Contracts reference this customer. | F15: CUST-021, CON-031
A16: BR-CUST-11 | B16: AMC Customers | C16: Permissions | D16: Technician has read-only access to customers | E16: Permissions: Technician read:1 only. No create, write, delete on AMC Customers. | F16: CUST-020
A17: ▌ AMC Contract
A18: BR-CON-01 | B18: AMC Contract | C18: Mandatory Fields | D18: Start Date, End Date, No of Services required | E18: reqd:1 on all three. Save is blocked without any of these fields. | F18: CON-001, CON-002, CON-003, CON-004
A19: BR-CON-02 | B19: AMC Contract | C19: Auto-Naming | D19: Contract name follows AMC-.YY.MM.-.#### series | E19: naming_series: "AMC-.YY.MM.-.####". Provides month-stamped, chronological IDs. | F19: CON-005
A20: BR-CON-03 | B20: AMC Contract | C20: Date Logic | D20: End Date must be >= Start Date | E20: Business rule: end < start must be rejected. Same-day and multi-year spans are valid. | F20: CON-006, CON-007, CON-008
A21: BR-CON-04 | B21: AMC Contract | C21: Service Count | D21: No of Services drives Maintenance Schedule rows | E21: Select 1-12. Must generate exactly that many rows in Maintenance Schedule child table. | F21: CON-009 to CON-013, CON-029
A22: BR-CON-05 | B22: AMC Contract | C22: Service Count | D22: Schedule dates must fall within contract period | E22: Each generated date >= start_date and <= end_date. | F22: CON-012
A23: BR-CON-06 | B23: AMC Contract | C23: Customer Linkage | D23: Branch filtered by selected Customer | E23: link_filters: Customer Branch.customer = doc.customer. Branch only shows that customer's branches. | F23: CON-015, CON-016, CON-017
A24: BR-CON-07 | B24: AMC Contract | C24: Contact Linkage | D24: Contact Person filtered by selected Branch | E24: link_filters: Customer Contact.branch = doc.branch. Mobile auto-fetched via fetch_from. | F24: CON-018, CUST-016, CUST-017
A25: BR-CON-08 | B25: AMC Contract | C25: Equipment | D25: Maintenance Schedule stores equipment per visit | E25: Child table columns: Equipment, Quantity, Unit, Description. Per-visit specification. | F25: CON-014, CON-026
A26: BR-CON-09 | B26: AMC Contract | C26: Status | D26: Status: blank / Active / Inactive | E26: Select field. Blank by default. Active enables service call dispatch; Inactive suspends it. | F26: CON-019, CON-020, CON-021
A27: BR-CON-10 | B27: AMC Contract | C27: Workflow | D27: is_submittable: Draft > Submit > Cancel | E27: is_submittable:1. Submitted = read-only. Cancelled = immutable. Technician cannot cancel. | F27: CON-022, CON-023, CON-025
A28: BR-CON-11 | B28: AMC Contract | C28: Workflow | D28: Submitted contract can be Amended | E28: amended_from field links to original. Amend creates new draft; original is cancelled on re-submit. | F28: CON-024
A29: BR-CON-12 | B29: AMC Contract | C29: Service Calls | D29: Service Calls tab shows generated calls | E29: service_calls_html renders calls. Count must equal No of Services after processing. | F29: CON-027, CON-028, CON-029
... A31: BR-CON-14 | B31: AMC Contract | C31: Permissions | D31: Technician: create/write/submit, no cancel/delete | E31: Technician permissions: create, write, read, submit, email, export, print, share, select. No cancel or delete. | F31: CON-032, CUST-020
A32: ▌ Vendor
A33: BR-VEN-01 | B33: Vendor | C33: Creation | D33: Vendor Name is mandatory | E33: Vendor Name is the primary identifier. Save is blocked without it. | F33: VEN-001, VEN-002, VEN-027, VEN-036
A34: BR-VEN-02 | B34: Vendor | C34: Creation | D34: Vendor Type: Company or Individual | E34: Type field classifies the vendor entity. Defaults to Company if blank. | F34: VEN-003, VEN-004, VEN-029, VEN-030
A35: BR-VEN-03 | B35: Vendor | C35: Primary Contact | D35: Contact details validated (phone, email) | E35: Mobile No and Email must match valid formats. | F35: VEN-005 to VEN-009
A36: BR-VEN-04 | B36: Vendor | C36: Tax ID | D36: PAN must match valid format or be blank | E36: PAN: 10-char alphanumeric. Optional field — blank is allowed. | F36: VEN-010, VEN-011, VEN-013
A37: BR-VEN-05 | B37: Vendor | C37: Tax ID | D37: PAN is unique across all vendors | E37: unique:1 on PAN. Two vendors cannot share the same PAN. | F37: VEN-012
A38: BR-VEN-06 | B38: Vendor | C38: Address | D38: Registered Address is a free-text field | E38: Text area, accepts special characters. Saved as-is. | F38: VEN-014, VEN-015, VEN-016
A39: BR-VEN-07 | B39: Vendor | C39: Address Table | D39: Address table stores multiple addresses | E39: Child table: Name, City, State, Mobile No per row. | F39: VEN-017 to VEN-022, VEN-025
A40: BR-VEN-08 | B40: Vendor | C40: Address Table | D40: GST No in address row validated | E40: GST must be valid 15-char GSTIN format per address row. | F40: VEN-023, VEN-024
A41: BR-VEN-09 | B41: Vendor | C41: Address Table | D41: Duplicate GST across address rows is blocked | E41: Each address row GST must be unique within the vendor. | F41: VEN-026
A42: BR-VEN-10 | B42: Vendor | C42: Editing | D42: All fields editable after creation | E42: Vendor records can be updated at any time. | F42: VEN-031 to VEN-035
A43: BR-VEN-11 | B43: Vendor | C43: Form Actions | D43: Standard form save/duplicate/delete actions | E43: ERPNext standard actions: Save, Duplicate, Delete apply to Vendor. | F43: VEN-036 to VEN-040
A44: ▌ Attendance
A45: BR-ATT-01 | B45: Attendance | C45: Creation | D45: Employee, Status, Date are mandatory | E45: reqd:1 on all three. Save is blocked without any of these fields. | F45: ATT-001, ATT-002, ATT-041 to ATT-043, ATT-050
A46: BR-ATT-02 | B46: Attendance | C46: Creation | D46: Company and Shift are optional fields | E46: Company and Shift enhance the record but are not required for save. | F46: ATT-002
A47: BR-ATT-03 | B47: Attendance | C47: Status | D47: Status: Present/Absent/Leave/Half Day | E47: Select field with 4 options. Mandatory. Controls Late/Early flag validity. | F47: ATT-003 to ATT-006, ATT-019 to ATT-021, ATT-042
A48: BR-ATT-04 | B48: Attendance | C48: Auto-Naming | D48: Series auto-generated: HR-ATT-.YYYY.- | E48: Naming series produces unique, year-stamped attendance IDs. Read-only. | F48: ATT-007 to ATT-009
A49: BR-ATT-05 | B49: Attendance | C49: Employee | D49: Employee must be a valid ERPNext Employee | E49: Link field — only existing Employee records accepted. Mandatory. | F49: ATT-010 to ATT-012, ATT-041
A50: BR-ATT-06 | B50: Attendance | C50: Duplicate | D50: Duplicate Employee+Date combination blocked | E50: One attendance record per employee per date. Duplicate insert must fail. | F50: ATT-013
A51: BR-ATT-07 | B51: Attendance | C51: Date | D51: Attendance Date is mandatory, any date valid | E51: Date field: past, present, and future dates all accepted. Blank not allowed. | F51: ATT-014 to ATT-018, ATT-043
A52: BR-ATT-08 | B52: Attendance | C52: Company | D52: Company auto-populates from employee record | E52: Company field fetched from Employee.company. Can be manually overridden. | F52: ATT-022 to ATT-024
A53: BR-ATT-09 | B53: Attendance | C53: Shift | D53: Shift is optional, auto-populates if assigned | E53: Shift Type linked to employee assignment. Optional; blank is allowed. | F53: ATT-025 to ATT-028
A54: BR-ATT-10 | B54: Attendance | C54: Late Entry | D54: Late Entry valid only with Present status | E54: Late Entry checkbox meaningful only when Status = Present. Invalid for Absent. | F54: ATT-029 to ATT-033
A55: BR-ATT-11 | B55: Attendance | C55: Early Exit | D55: Early Exit valid only with Present status | E55: Early Exit checkbox meaningful only when Status = Present. Invalid for Absent. | F55: ATT-034 to ATT-038
A56: BR-ATT-12 | B56: Attendance | C56: Combination | D56: Late Entry + Early Exit can combine (Present) | E56: Both flags can be set simultaneously only when Status = Present. | F56: ATT-039, ATT-040
... A58: BR-ATT-14 | B58: Attendance | C58: Form Actions | D58: Standard save flow with status indicators | E58: ERPNext "Not Saved" / "Saved" status shown in form header. | F58: ATT-050 to ATT-052
A59: ▌ Expense Claim
A60: BR-EXP-01 | B60: Expense Claim | C60: Creation | D60: Employee + Company + Approver are core mandatory fields | E60: ERPNext v15: from_employee (reqd), company (reqd). Record saved as Draft. Series HR-EXP-.YYYY.- auto-assigned. | F60: EXP-001, EXP-002, EXP-047, EXP-048, EXP-055
A61: BR-EXP-02 | B61: Expense Claim | C61: Creation | D61: Department auto-fetches from Employee master | E61: department field: fetch_from = employee.department. Read-only after auto-fill; can be overridden. | F61: EXP-002, EXP-009
A62: BR-EXP-03 | B62: Expense Claim | C62: Auto-Naming | D62: Series: HR-EXP-.YYYY.- (year-based, read-only) | E62: naming_series default HR-EXP-.YYYY.-. Unique per record, auto-incremented. Cannot be manually edited. | F62: EXP-003, EXP-004, EXP-005
A63: BR-EXP-04 | B63: Expense Claim | C63: Employee | D63: from_employee: Link → Employee, mandatory | E63: reqd:1. Only active ERPNext v15 Employees accepted. Department and cost_center auto-fetched on select. | F63: EXP-006, EXP-007, EXP-008, EXP-009, EXP-047
A64: BR-EXP-05 | B64: Expense Claim | C64: Company | D64: company: mandatory; GSTIN auto-fetched, read-only | E64: reqd:1. company_gstin fetch_from company.gstin. GSTIN field set as read_only:1 in v15. | F64: EXP-010, EXP-011, EXP-012, EXP-013, EXP-048
A65: BR-EXP-06 | B65: Expense Claim | C65: Approver | D65: expense_approver: mandatory; must be valid HR user | E65: reqd:1. Link → User. Only users with Expense Approver role. Cannot approve own claim. | F65: EXP-014, EXP-015, EXP-016, EXP-049
A66: BR-EXP-07 | B66: Expense Claim | C66: Approval Status | D66: approval_status: Draft → Approved / Rejected / Returned | E66: Select field: Draft (default), Approved, Rejected, Returned. Only approver can change from Draft. Editing blocked once Approved. | F66: EXP-017, EXP-018, EXP-019, EXP-020, EXP-054
A67: BR-EXP-08 | B67: Expense Claim | C67: Expenses Table | D67: expenses child table: expense_date, expense_type, amount are reqd | E67: Child table fieldname: expenses. reqd: expense_date, expense_claim_type, amount. amount must be > 0. description optional. | F67: EXP-021 to EXP-030, EXP-033, EXP-050
A68: BR-EXP-09 | B68: Expense Claim | C68: Expense Type | D68: expense_claim_type: Link → Expense Claim Type master | E68: Must exist in Expense Claim Type DocType. Controls default account and optional per-type limit. | F68: EXP-025, EXP-026
A69: BR-EXP-10 | B69: Expense Claim | C69: Sanctioned Amount | D69: sanctioned_amount per row ≤ amount; auto-equals amount by default | E69: sanctioned_amount defaults to amount value. Validation blocks sanctioned > claimed at row level. | F69: EXP-031, EXP-032
A70: BR-EXP-11 | B70: Expense Claim | C70: Totals | D70: total_claimed_amount and grand_total auto-calculated | E70: total_claimed_amount = SUM(expenses.amount). grand_total = total_sanctioned + taxes. Both read-only calculated fields. | F70: EXP-033, EXP-040
A71: BR-EXP-12 | B71: Expense Claim | C71: Taxes & Charges | D71: taxes child table: account_head and tax_amount required per row | E71: Child table fieldname: taxes. account_head (Link → Account) reqd. tax_amount reqd. Rows optional — no tax rows is valid. | F71: EXP-034 to EXP-040
... A75: BR-EXP-16 | B75: Expense Claim | C75: Form Actions | D75: Submit/Cancel/Duplicate per ERPNext v15 workflow | E75: is_submittable:1. Submit creates JE when Approved. Cancel reverses JE. Duplicate creates new Draft copy. | F75: EXP-055, EXP-056, EXP-057, EXP-058, EXP-059, EXP-060
A76: ▌ Leave Application
A77: BR-LEA-01 | B77: Leave Application | C77: Creation | D77: Employee + Leave Type + Dates are core mandatory fields | E77: ERPNext v15: employee (reqd), leave_type (reqd), from_date (reqd), to_date (reqd). Defaults status = Open. | F77: LEA-001, LEA-002, LEA-049 to LEA-053, LEA-059
A78: BR-LEA-02 | B78: Leave Application | C78: Creation | D78: Optional header fields: Company, Leave Approver, Reason | E78: company auto-populates. leave_approver mandatory in v15. description (reason) is optional. | F78: LEA-002
A79: BR-LEA-03 | B79: Leave Application | C79: Auto-Naming | D79: Series: HR-LAP-.YYYY.- (year-based, read-only) | E79: naming_series default HR-LAP-.YYYY.-. Unique per record, auto-incremented. Cannot be manually edited. | F79: LEA-003, LEA-004, LEA-005
A80: BR-LEA-04 | B80: Leave Application | C80: Employee | D80: employee: Link → Employee, mandatory | E80: reqd:1. Only active Employees. Company and department auto-fetched on selection. | F80: LEA-006, LEA-007, LEA-008, LEA-049
A81: BR-LEA-05 | B81: Leave Application | C81: Leave Type | D81: leave_type: Link → Leave Type, mandatory | E81: reqd:1. Must exist in Leave Type master. Controls balance pool, LWP, allow_negative settings. | F81: LEA-009, LEA-010, LEA-011, LEA-050
A82: BR-LEA-06 | B82: Leave Application | C82: Leave Balance | D82: Leave balance checked on save; deducted on Approve; restored on Cancel | E82: total_leave_days checked against available allocation. balance_leaves displayed. Insufficient balance blocks submit (unless allow_negative_balance). | F82: LEA-012, LEA-039 to LEA-043
A83: BR-LEA-07 | B83: Leave Application | C83: Company | D83: company: mandatory; auto-fetched from Employee master | E83: reqd:1. fetch_from = employee.company. Determines holiday list for day calculation. | F83: LEA-013, LEA-014, LEA-015
A84: BR-LEA-08 | B84: Leave Application | C84: Date Range | D84: from_date and to_date: mandatory; from_date ≤ to_date | E84: reqd:1 on both. Validation: from_date cannot be after to_date. Past dates controlled by Leave Type settings in v15. | F84: LEA-016 to LEA-021, LEA-051 to LEA-053
A85: BR-LEA-09 | B85: Leave Application | C85: Duration | D85: total_leave_days auto-calculated; excludes holidays and weekly offs | E85: total_leave_days = working days between from_date and to_date per Holiday List. Half Day = 0.5. | F85: LEA-022, LEA-028
A86: BR-LEA-10 | B86: Leave Application | C86: Half Day | D86: half_day: Check field; valid only when from_date = to_date | E86: half_day = 1 sets total_leave_days = 0.5. ERPNext v15 blocks half_day when from_date ≠ to_date. Also requires half_day_date. | F86: LEA-023, LEA-024, LEA-025, LEA-026, LEA-027
A87: BR-LEA-11 | B87: Leave Application | C87: Reason | D87: description (Reason): optional free-text field | E87: No format restriction. Accepts any text including special characters. Not required for save or submit. | F87: LEA-029, LEA-030, LEA-031
A88: BR-LEA-12 | B88: Leave Application | C88: Leave Approver | D88: leave_approver: mandatory; must hold approval authority | E88: reqd:1 in v15. Link → User. Approver must be assigned in Employee master or Leave Approver list. Cannot self-approve. | F88: LEA-032, LEA-033, LEA-034, LEA-035, LEA-048
... A92: BR-LEA-16 | B92: Leave Application | C92: Form Actions | D92: Submit/Cancel/Duplicate/Delete per ERPNext v15 | E92: Submit changes status per workflow. Cancel restores balance and attendance. Delete only on Open draft. Duplicate creates new copy. | F92: LEA-059, LEA-060, LEA-061, LEA-062, LEA-063, LEA-064, LEA-065
A93: ▌ Service Call
A94: BR-SC-01 | B94: Service Call | C94: Creation | D94: Customer and Service Type are mandatory | E94: customer (Link → AMC Customers, reqd:1) and service_type are the minimum required fields. Save blocked without them. | F94: SC-001, SC-002, SC-039
A95: BR-SC-02 | B95: Service Call | C95: Creation | D95: Title, Description, Priority are optional header fields | E95: title (Data), description (Text Area), and priority (Select) enhance the record but are not required for save. | F95: SC-002
A96: BR-SC-03 | B96: Service Call | C96: Customer Validation | D96: Customer must be a valid AMC Customer; branch auto-populates | E96: Link field to AMC Customers DocType. Invalid entries rejected. Branch Locations child table populates based on selected customer. | F96: SC-004, SC-005, SC-006, SC-007
A97: BR-SC-04 | B97: Service Call | C97: Location | D97: Branch filtered by customer; Contact Person filtered by branch | E97: branch link_filters: Customer Branch.customer = doc.customer. contact_person further filtered by selected branch. | F97: SC-008, SC-009
A98: BR-SC-05 | B98: Service Call | C98: Technician | D98: Technician assignment is optional but must be unique per Service Call | E98: technician (Link → Employee with Technician role). Optional at creation. Duplicate assignment (same tech on same SC) blocked. | F98: SC-010, SC-011, SC-012, SC-013, SC-044
A99: BR-SC-06 | B99: Service Call | C99: Priority | D99: Priority: High / Medium / Low (Select field) | E99: priority Select field with options: High, Medium, Low. Controls SLA tracking and escalation rules. | F99: SC-014, SC-015
A100: BR-SC-07 | B100: Service Call | C100: Status Workflow | D100: Status: Draft → Assigned → In Progress → Completed; invalid transitions blocked | E100: Workflow states: Draft, Assigned, In Progress, Completed, Cancelled. Transitions validated — skipping states rejected. Completed/Cancelled restrict edits. | F100: SC-016, SC-017, SC-018, SC-047
A101: BR-SC-08 | B101: Service Call | C101: Service Items | D101: service_items child table: Item, Qty required per row; stock checked | E101: Child table with item (Link → Item), qty (mandatory, > 0), rate, amount. Out-of-stock item flags warning. Row operations: add, edit, delete. | F101: SC-003, SC-023, SC-024, SC-025, SC-026, SC-027
A102: BR-SC-09 | B102: Service Call | C102: Service Date & Time | D102: service_date is mandatory; past dates rejected; start/end time tracked | E102: service_date (reqd:1). Past dates blocked by validation. service_start_time and service_end_time recorded for duration calculation. | F102: SC-019, SC-020, SC-021, SC-022
A103: BR-SC-10 | B103: Service Call | C103: Billing | D103: total_cost auto-calculated; discount and charges adjust total; billable flag controls invoicing | E103: total_cost = SUM(service_items.amount) + additional_charges - discount. is_billable checkbox determines if SC can generate a Sales Invoice. | F103: SC-028, SC-029, SC-030, SC-031
A104: BR-SC-11 | B104: Service Call | C104: SLA & Warranty | D104: Warranty status and SLA response time tracked per Service Call | E104: under_warranty (Check) flag set based on Customer warranty records. sla_response_time tracked from creation timestamp. Overdue SLA flagged. | F104: SC-032, SC-033, SC-034
A105: BR-SC-12 | B105: Service Call | C105: Documentation | D105: Attachments, internal notes, and customer remarks supported | E105: Standard Frappe file attachments per record. internal_notes (Text, not visible to customer). customer_remarks (Text, customer-visible). | F105: SC-035, SC-036, SC-037, SC-038
... A109: BR-SC-16 | B109: Service Call | C109: Permissions | D109: Role-based access: Technician (own), Customer (own), Manager (all) | E109: Technician role: list view filtered to assigned SCs only. Customer portal: own SCs only. Service Manager: full access including approve/reject. | F109: SC-048, SC-049, SC-050
